{"meta": {"page": {"size": 50, "number": 1}, "count": 33}, "data": {"event_sessions": [{"capacity": 15, "tags": [], "is_listed": true, "session_number": 23455, "start_date_time": "2023-11-16T17:00:00.000Z", "end_date_time": "2023-11-16T17:10:00.000Z", "location": {"id": "604bff314dde50e2de52c0e5", "name": "Hanauma Bay Orientation"}, "meta_data": {"tickets_issued": 22, "tickets_available": 0, "tickets_issued_and_invalid": 7, "tickets_issued_and_valid": 15, "last_ticket_created_at": "2023-11-14T17:17:09.766Z"}, "event_id": "607fcb1a9196e149ac206742", "app_id": "hanauma_bay", "__v": 0, "created_at": "2023-06-20T23:11:09.981Z", "updated_at": "2023-11-14T17:17:09.779Z", "id": "6492320d131dfb97125a73e3", "local_date_and_time": {"timezone": "GMT-10:00", "timezone_short": "GMT-10", "start_date": "11/16/2023", "start_time": "7:00 AM", "start_day_of_the_week": "Thursday", "end_date": "11/16/2023", "end_time": "7:10 AM", "end_day_of_the_week": "Thursday", "last_ticket_created_at": "Nov 14 at 7:17:09 AM"}}, {"capacity": 15, "tags": [], "is_listed": true, "session_number": 23456, "start_date_time": "2023-11-16T17:10:00.000Z", "end_date_time": "2023-11-16T17:20:00.000Z", "location": {"id": "604bff314dde50e2de52c0e5", "name": "Hanauma Bay Orientation"}, "meta_data": {"tickets_issued": 15, "tickets_available": 0, "tickets_issued_and_invalid": 0, "tickets_issued_and_valid": 15, "last_ticket_created_at": "2023-11-14T17:04:31.206Z"}, "event_id": "607fcb1a9196e149ac206742", "app_id": "hanauma_bay", "__v": 0, "created_at": "2023-06-20T23:11:09.981Z", "updated_at": "2023-11-14T17:04:31.215Z", "id": "6492320d131dfb03c75a73e4", "local_date_and_time": {"timezone": "GMT-10:00", "timezone_short": "GMT-10", "start_date": "11/16/2023", "start_time": "7:10 AM", "start_day_of_the_week": "Thursday", "end_date": "11/16/2023", "end_time": "7:20 AM", "end_day_of_the_week": "Thursday", "last_ticket_created_at": "Nov 14 at 7:04:31 AM"}}, {"capacity": 15, "tags": [], "is_listed": true, "session_number": 23457, "start_date_time": "2023-11-16T17:20:00.000Z", "end_date_time": "2023-11-16T17:30:00.000Z", "location": {"id": "604bff314dde50e2de52c0e5", "name": "Hanauma Bay Orientation"}, "meta_data": {"tickets_issued": 18, "tickets_available": 0, "tickets_issued_and_invalid": 3, "tickets_issued_and_valid": 15, "last_ticket_created_at": "2023-11-14T17:13:22.020Z"}, "event_id": "607fcb1a9196e149ac206742", "app_id": "hanauma_bay", "__v": 0, "created_at": "2023-06-20T23:11:09.981Z", "updated_at": "2023-11-14T17:13:22.029Z", "id": "6492320d131dfb5f845a73e5", "local_date_and_time": {"timezone": "GMT-10:00", "timezone_short": "GMT-10", "start_date": "11/16/2023", "start_time": "7:20 AM", "start_day_of_the_week": "Thursday", "end_date": "11/16/2023", "end_time": "7:30 AM", "end_day_of_the_week": "Thursday", "last_ticket_created_at": "Nov 14 at 7:13:22 AM"}}, {"capacity": 15, "tags": [], "is_listed": true, "session_number": 23458, "start_date_time": "2023-11-16T17:30:00.000Z", "end_date_time": "2023-11-16T17:40:00.000Z", "location": {"id": "604bff314dde50e2de52c0e5", "name": "Hanauma Bay Orientation"}, "meta_data": {"tickets_issued": 15, "tickets_available": 0, "tickets_issued_and_invalid": 0, "tickets_issued_and_valid": 15, "last_ticket_created_at": "2023-11-14T17:04:07.883Z"}, "event_id": "607fcb1a9196e149ac206742", "app_id": "hanauma_bay", "__v": 0, "created_at": "2023-06-20T23:11:09.981Z", "updated_at": "2023-11-14T17:04:07.893Z", "id": "6492320d131dfba6445a73e6", "local_date_and_time": {"timezone": "GMT-10:00", "timezone_short": "GMT-10", "start_date": "11/16/2023", "start_time": "7:30 AM", "start_day_of_the_week": "Thursday", "end_date": "11/16/2023", "end_time": "7:40 AM", "end_day_of_the_week": "Thursday", "last_ticket_created_at": "Nov 14 at 7:04:07 AM"}}, {"capacity": 15, "tags": [], "is_listed": true, "session_number": 23459, "start_date_time": "2023-11-16T17:40:00.000Z", "end_date_time": "2023-11-16T18:00:00.000Z", "location": {"id": "604bff314dde50e2de52c0e5", "name": "Hanauma Bay Orientation"}, "meta_data": {"tickets_issued": 23, "tickets_available": 0, "tickets_issued_and_invalid": 8, "tickets_issued_and_valid": 15, "last_ticket_created_at": "2023-11-14T17:29:49.274Z"}, "event_id": "607fcb1a9196e149ac206742", "app_id": "hanauma_bay", "__v": 0, "created_at": "2023-06-20T23:11:09.981Z", "updated_at": "2023-11-14T17:29:49.291Z", "id": "6492320d131dfb7d2c5a73e7", "local_date_and_time": {"timezone": "GMT-10:00", "timezone_short": "GMT-10", "start_date": "11/16/2023", "start_time": "7:40 AM", "start_day_of_the_week": "Thursday", "end_date": "11/16/2023", "end_time": "8:00 AM", "end_day_of_the_week": "Thursday", "last_ticket_created_at": "Nov 14 at 7:29:49 AM"}}, {"capacity": 35, "tags": [], "is_listed": true, "session_number": 23460, "start_date_time": "2023-11-16T18:00:00.000Z", "end_date_time": "2023-11-16T18:10:00.000Z", "location": {"id": "604bff314dde50e2de52c0e5", "name": "Hanauma Bay Orientation"}, "meta_data": {"tickets_issued": 41, "tickets_available": 0, "tickets_issued_and_invalid": 6, "tickets_issued_and_valid": 35, "last_ticket_created_at": "2023-11-14T17:12:25.114Z"}, "event_id": "607fcb1a9196e149ac206742", "app_id": "hanauma_bay", "__v": 0, "created_at": "2023-06-20T23:11:09.981Z", "updated_at": "2023-11-14T17:12:25.124Z", "id": "6492320d131dfb09565a73e8", "local_date_and_time": {"timezone": "GMT-10:00", "timezone_short": "GMT-10", "start_date": "11/16/2023", "start_time": "8:00 AM", "start_day_of_the_week": "Thursday", "end_date": "11/16/2023", "end_time": "8:10 AM", "end_day_of_the_week": "Thursday", "last_ticket_created_at": "Nov 14 at 7:12:25 AM"}}, {"capacity": 35, "tags": [], "is_listed": true, "session_number": 23461, "start_date_time": "2023-11-16T18:10:00.000Z", "end_date_time": "2023-11-16T18:20:00.000Z", "location": {"id": "604bff314dde50e2de52c0e5", "name": "Hanauma Bay Orientation"}, "meta_data": {"tickets_issued": 47, "tickets_available": 0, "tickets_issued_and_invalid": 12, "tickets_issued_and_valid": 35, "last_ticket_created_at": "2023-11-14T17:21:42.685Z"}, "event_id": "607fcb1a9196e149ac206742", "app_id": "hanauma_bay", "__v": 0, "created_at": "2023-06-20T23:11:09.981Z", "updated_at": "2023-11-14T17:21:42.704Z", "id": "6492320d131dfb9cad5a73e9", "local_date_and_time": {"timezone": "GMT-10:00", "timezone_short": "GMT-10", "start_date": "11/16/2023", "start_time": "8:10 AM", "start_day_of_the_week": "Thursday", "end_date": "11/16/2023", "end_time": "8:20 AM", "end_day_of_the_week": "Thursday", "last_ticket_created_at": "Nov 14 at 7:21:42 AM"}}, {"capacity": 35, "tags": [], "is_listed": true, "session_number": 23462, "start_date_time": "2023-11-16T18:20:00.000Z", "end_date_time": "2023-11-16T18:30:00.000Z", "location": {"id": "604bff314dde50e2de52c0e5", "name": "Hanauma Bay Orientation"}, "meta_data": {"tickets_issued": 52, "tickets_available": 0, "tickets_issued_and_invalid": 17, "tickets_issued_and_valid": 35, "last_ticket_created_at": "2023-11-14T17:16:09.396Z"}, "event_id": "607fcb1a9196e149ac206742", "app_id": "hanauma_bay", "__v": 0, "created_at": "2023-06-20T23:11:09.981Z", "updated_at": "2023-11-14T17:16:09.415Z", "id": "6492320d131dfbfd695a73ea", "local_date_and_time": {"timezone": "GMT-10:00", "timezone_short": "GMT-10", "start_date": "11/16/2023", "start_time": "8:20 AM", "start_day_of_the_week": "Thursday", "end_date": "11/16/2023", "end_time": "8:30 AM", "end_day_of_the_week": "Thursday", "last_ticket_created_at": "Nov 14 at 7:16:09 AM"}}, {"capacity": 35, "tags": [], "is_listed": true, "session_number": 23463, "start_date_time": "2023-11-16T18:30:00.000Z", "end_date_time": "2023-11-16T18:40:00.000Z", "location": {"id": "604bff314dde50e2de52c0e5", "name": "Hanauma Bay Orientation"}, "meta_data": {"tickets_issued": 53, "tickets_available": 0, "tickets_issued_and_invalid": 18, "tickets_issued_and_valid": 35, "last_ticket_created_at": "2023-11-14T17:14:17.571Z"}, "event_id": "607fcb1a9196e149ac206742", "app_id": "hanauma_bay", "__v": 0, "created_at": "2023-06-20T23:11:09.982Z", "updated_at": "2023-11-14T17:14:17.596Z", "id": "6492320d131dfbbbf95a73eb", "local_date_and_time": {"timezone": "GMT-10:00", "timezone_short": "GMT-10", "start_date": "11/16/2023", "start_time": "8:30 AM", "start_day_of_the_week": "Thursday", "end_date": "11/16/2023", "end_time": "8:40 AM", "end_day_of_the_week": "Thursday", "last_ticket_created_at": "Nov 14 at 7:14:17 AM"}}, {"capacity": 35, "tags": [], "is_listed": true, "session_number": 23464, "start_date_time": "2023-11-16T18:40:00.000Z", "end_date_time": "2023-11-16T19:00:00.000Z", "location": {"id": "604bff314dde50e2de52c0e5", "name": "Hanauma Bay Orientation"}, "meta_data": {"tickets_issued": 55, "tickets_available": 0, "tickets_issued_and_invalid": 20, "tickets_issued_and_valid": 35, "last_ticket_created_at": "2023-11-14T17:38:25.185Z"}, "event_id": "607fcb1a9196e149ac206742", "app_id": "hanauma_bay", "__v": 0, "created_at": "2023-06-20T23:11:09.982Z", "updated_at": "2023-11-14T17:38:50.715Z", "id": "6492320d131dfbd3f55a73ec", "local_date_and_time": {"timezone": "GMT-10:00", "timezone_short": "GMT-10", "start_date": "11/16/2023", "start_time": "8:40 AM", "start_day_of_the_week": "Thursday", "end_date": "11/16/2023", "end_time": "9:00 AM", "end_day_of_the_week": "Thursday", "last_ticket_created_at": "Nov 14 at 7:38:25 AM"}}, {"capacity": 35, "tags": [], "is_listed": true, "session_number": 23465, "start_date_time": "2023-11-16T19:00:00.000Z", "end_date_time": "2023-11-16T19:10:00.000Z", "location": {"id": "604bff314dde50e2de52c0e5", "name": "Hanauma Bay Orientation"}, "meta_data": {"tickets_issued": 43, "tickets_available": 0, "tickets_issued_and_invalid": 8, "tickets_issued_and_valid": 35, "last_ticket_created_at": "2023-11-14T17:29:00.598Z"}, "event_id": "607fcb1a9196e149ac206742", "app_id": "hanauma_bay", "__v": 0, "created_at": "2023-06-20T23:11:09.982Z", "updated_at": "2023-11-14T17:29:00.630Z", "id": "6492320d131dfb72a05a73ed", "local_date_and_time": {"timezone": "GMT-10:00", "timezone_short": "GMT-10", "start_date": "11/16/2023", "start_time": "9:00 AM", "start_day_of_the_week": "Thursday", "end_date": "11/16/2023", "end_time": "9:10 AM", "end_day_of_the_week": "Thursday", "last_ticket_created_at": "Nov 14 at 7:29:00 AM"}}, {"capacity": 35, "tags": [], "is_listed": true, "session_number": 23466, "start_date_time": "2023-11-16T19:10:00.000Z", "end_date_time": "2023-11-16T19:20:00.000Z", "location": {"id": "604bff314dde50e2de52c0e5", "name": "Hanauma Bay Orientation"}, "meta_data": {"tickets_issued": 43, "tickets_available": 0, "tickets_issued_and_invalid": 8, "tickets_issued_and_valid": 35, "last_ticket_created_at": "2023-11-14T17:22:19.948Z"}, "event_id": "607fcb1a9196e149ac206742", "app_id": "hanauma_bay", "__v": 0, "created_at": "2023-06-20T23:11:09.982Z", "updated_at": "2023-11-14T17:22:19.962Z", "id": "6492320d131dfb2a4f5a73ee", "local_date_and_time": {"timezone": "GMT-10:00", "timezone_short": "GMT-10", "start_date": "11/16/2023", "start_time": "9:10 AM", "start_day_of_the_week": "Thursday", "end_date": "11/16/2023", "end_time": "9:20 AM", "end_day_of_the_week": "Thursday", "last_ticket_created_at": "Nov 14 at 7:22:19 AM"}}, {"capacity": 35, "tags": [], "is_listed": true, "session_number": 23467, "start_date_time": "2023-11-16T19:20:00.000Z", "end_date_time": "2023-11-16T19:30:00.000Z", "location": {"id": "604bff314dde50e2de52c0e5", "name": "Hanauma Bay Orientation"}, "meta_data": {"tickets_issued": 44, "tickets_available": 0, "tickets_issued_and_invalid": 9, "tickets_issued_and_valid": 35, "last_ticket_created_at": "2023-11-14T17:15:43.172Z"}, "event_id": "607fcb1a9196e149ac206742", "app_id": "hanauma_bay", "__v": 0, "created_at": "2023-06-20T23:11:09.982Z", "updated_at": "2023-11-14T17:15:43.185Z", "id": "6492320d131dfb5ee05a73ef", "local_date_and_time": {"timezone": "GMT-10:00", "timezone_short": "GMT-10", "start_date": "11/16/2023", "start_time": "9:20 AM", "start_day_of_the_week": "Thursday", "end_date": "11/16/2023", "end_time": "9:30 AM", "end_day_of_the_week": "Thursday", "last_ticket_created_at": "Nov 14 at 7:15:43 AM"}}, {"capacity": 35, "tags": [], "is_listed": true, "session_number": 23468, "start_date_time": "2023-11-16T19:30:00.000Z", "end_date_time": "2023-11-16T19:40:00.000Z", "location": {"id": "604bff314dde50e2de52c0e5", "name": "Hanauma Bay Orientation"}, "meta_data": {"tickets_issued": 38, "tickets_available": 0, "tickets_issued_and_invalid": 3, "tickets_issued_and_valid": 35, "last_ticket_created_at": "2023-11-14T17:04:31.109Z"}, "event_id": "607fcb1a9196e149ac206742", "app_id": "hanauma_bay", "__v": 0, "created_at": "2023-06-20T23:11:09.982Z", "updated_at": "2023-11-14T17:04:31.119Z", "id": "6492320d131dfb61115a73f0", "local_date_and_time": {"timezone": "GMT-10:00", "timezone_short": "GMT-10", "start_date": "11/16/2023", "start_time": "9:30 AM", "start_day_of_the_week": "Thursday", "end_date": "11/16/2023", "end_time": "9:40 AM", "end_day_of_the_week": "Thursday", "last_ticket_created_at": "Nov 14 at 7:04:31 AM"}}, {"capacity": 35, "tags": [], "is_listed": true, "session_number": 23469, "start_date_time": "2023-11-16T19:40:00.000Z", "end_date_time": "2023-11-16T20:00:00.000Z", "location": {"id": "604bff314dde50e2de52c0e5", "name": "Hanauma Bay Orientation"}, "meta_data": {"tickets_issued": 45, "tickets_available": 0, "tickets_issued_and_invalid": 10, "tickets_issued_and_valid": 35, "last_ticket_created_at": "2023-11-14T17:59:55.333Z"}, "event_id": "607fcb1a9196e149ac206742", "app_id": "hanauma_bay", "__v": 0, "created_at": "2023-06-20T23:11:09.982Z", "updated_at": "2023-11-14T17:59:55.351Z", "id": "6492320d131dfb61c65a73f1", "local_date_and_time": {"timezone": "GMT-10:00", "timezone_short": "GMT-10", "start_date": "11/16/2023", "start_time": "9:40 AM", "start_day_of_the_week": "Thursday", "end_date": "11/16/2023", "end_time": "10:00 AM", "end_day_of_the_week": "Thursday", "last_ticket_created_at": "Nov 14 at 7:59:55 AM"}}, {"capacity": 35, "tags": [], "is_listed": true, "session_number": 23470, "start_date_time": "2023-11-16T20:00:00.000Z", "end_date_time": "2023-11-16T20:10:00.000Z", "location": {"id": "604bff314dde50e2de52c0e5", "name": "Hanauma Bay Orientation"}, "meta_data": {"tickets_issued": 41, "tickets_available": 0, "tickets_issued_and_invalid": 6, "tickets_issued_and_valid": 35, "last_ticket_created_at": "2023-11-14T17:15:05.796Z"}, "event_id": "607fcb1a9196e149ac206742", "app_id": "hanauma_bay", "__v": 0, "created_at": "2023-06-20T23:11:09.982Z", "updated_at": "2023-11-14T17:15:05.818Z", "id": "6492320d131dfb44945a73f2", "local_date_and_time": {"timezone": "GMT-10:00", "timezone_short": "GMT-10", "start_date": "11/16/2023", "start_time": "10:00 AM", "start_day_of_the_week": "Thursday", "end_date": "11/16/2023", "end_time": "10:10 AM", "end_day_of_the_week": "Thursday", "last_ticket_created_at": "Nov 14 at 7:15:05 AM"}}, {"capacity": 35, "tags": [], "is_listed": true, "session_number": 23471, "start_date_time": "2023-11-16T20:10:00.000Z", "end_date_time": "2023-11-16T20:20:00.000Z", "location": {"id": "604bff314dde50e2de52c0e5", "name": "Hanauma Bay Orientation"}, "meta_data": {"tickets_issued": 45, "tickets_available": 0, "tickets_issued_and_invalid": 10, "tickets_issued_and_valid": 35, "last_ticket_created_at": "2023-11-15T02:44:26.446Z"}, "event_id": "607fcb1a9196e149ac206742", "app_id": "hanauma_bay", "__v": 0, "created_at": "2023-06-20T23:11:09.982Z", "updated_at": "2023-11-15T02:44:26.465Z", "id": "6492320d131dfbe6355a73f3", "local_date_and_time": {"timezone": "GMT-10:00", "timezone_short": "GMT-10", "start_date": "11/16/2023", "start_time": "10:10 AM", "start_day_of_the_week": "Thursday", "end_date": "11/16/2023", "end_time": "10:20 AM", "end_day_of_the_week": "Thursday", "last_ticket_created_at": "Nov 14 at 4:44:26 PM"}}, {"capacity": 35, "tags": [], "is_listed": true, "session_number": 23472, "start_date_time": "2023-11-16T20:20:00.000Z", "end_date_time": "2023-11-16T20:30:00.000Z", "location": {"id": "604bff314dde50e2de52c0e5", "name": "Hanauma Bay Orientation"}, "meta_data": {"tickets_issued": 39, "tickets_available": 0, "tickets_issued_and_invalid": 4, "tickets_issued_and_valid": 35, "last_ticket_created_at": "2023-11-14T17:05:36.524Z"}, "event_id": "607fcb1a9196e149ac206742", "app_id": "hanauma_bay", "__v": 0, "created_at": "2023-06-20T23:11:09.982Z", "updated_at": "2023-11-14T17:05:36.540Z", "id": "6492320d131dfb206a5a73f4", "local_date_and_time": {"timezone": "GMT-10:00", "timezone_short": "GMT-10", "start_date": "11/16/2023", "start_time": "10:20 AM", "start_day_of_the_week": "Thursday", "end_date": "11/16/2023", "end_time": "10:30 AM", "end_day_of_the_week": "Thursday", "last_ticket_created_at": "Nov 14 at 7:05:36 AM"}}, {"capacity": 35, "tags": [], "is_listed": true, "session_number": 23473, "start_date_time": "2023-11-16T20:30:00.000Z", "end_date_time": "2023-11-16T20:40:00.000Z", "location": {"id": "604bff314dde50e2de52c0e5", "name": "Hanauma Bay Orientation"}, "meta_data": {"tickets_issued": 37, "tickets_available": 0, "tickets_issued_and_invalid": 2, "tickets_issued_and_valid": 35, "last_ticket_created_at": "2023-11-14T17:15:31.004Z"}, "event_id": "607fcb1a9196e149ac206742", "app_id": "hanauma_bay", "__v": 0, "created_at": "2023-06-20T23:11:09.982Z", "updated_at": "2023-11-14T17:15:31.017Z", "id": "6492320d131dfbb46a5a73f5", "local_date_and_time": {"timezone": "GMT-10:00", "timezone_short": "GMT-10", "start_date": "11/16/2023", "start_time": "10:30 AM", "start_day_of_the_week": "Thursday", "end_date": "11/16/2023", "end_time": "10:40 AM", "end_day_of_the_week": "Thursday", "last_ticket_created_at": "Nov 14 at 7:15:31 AM"}}, {"capacity": 35, "tags": [], "is_listed": true, "session_number": 23474, "start_date_time": "2023-11-16T20:40:00.000Z", "end_date_time": "2023-11-16T21:00:00.000Z", "location": {"id": "604bff314dde50e2de52c0e5", "name": "Hanauma Bay Orientation"}, "meta_data": {"tickets_issued": 43, "tickets_available": 0, "tickets_issued_and_invalid": 8, "tickets_issued_and_valid": 35, "last_ticket_created_at": "2023-11-14T17:26:21.411Z"}, "event_id": "607fcb1a9196e149ac206742", "app_id": "hanauma_bay", "__v": 0, "created_at": "2023-06-20T23:11:09.982Z", "updated_at": "2023-11-14T17:26:21.428Z", "id": "6492320d131dfb69af5a73f6", "local_date_and_time": {"timezone": "GMT-10:00", "timezone_short": "GMT-10", "start_date": "11/16/2023", "start_time": "10:40 AM", "start_day_of_the_week": "Thursday", "end_date": "11/16/2023", "end_time": "11:00 AM", "end_day_of_the_week": "Thursday", "last_ticket_created_at": "Nov 14 at 7:26:21 AM"}}, {"capacity": 35, "tags": [], "is_listed": true, "session_number": 23475, "start_date_time": "2023-11-16T21:00:00.000Z", "end_date_time": "2023-11-16T21:10:00.000Z", "location": {"id": "604bff314dde50e2de52c0e5", "name": "Hanauma Bay Orientation"}, "meta_data": {"tickets_issued": 40, "tickets_available": 0, "tickets_issued_and_invalid": 5, "tickets_issued_and_valid": 35, "last_ticket_created_at": "2023-11-14T17:03:37.456Z"}, "event_id": "607fcb1a9196e149ac206742", "app_id": "hanauma_bay", "__v": 0, "created_at": "2023-06-20T23:11:09.982Z", "updated_at": "2023-11-14T17:03:37.474Z", "id": "6492320d131dfb93f05a73f7", "local_date_and_time": {"timezone": "GMT-10:00", "timezone_short": "GMT-10", "start_date": "11/16/2023", "start_time": "11:00 AM", "start_day_of_the_week": "Thursday", "end_date": "11/16/2023", "end_time": "11:10 AM", "end_day_of_the_week": "Thursday", "last_ticket_created_at": "Nov 14 at 7:03:37 AM"}}, {"capacity": 35, "tags": [], "is_listed": true, "session_number": 23476, "start_date_time": "2023-11-16T21:10:00.000Z", "end_date_time": "2023-11-16T21:20:00.000Z", "location": {"id": "604bff314dde50e2de52c0e5", "name": "Hanauma Bay Orientation"}, "meta_data": {"tickets_issued": 40, "tickets_available": 0, "tickets_issued_and_invalid": 5, "tickets_issued_and_valid": 35, "last_ticket_created_at": "2023-11-14T17:07:26.054Z"}, "event_id": "607fcb1a9196e149ac206742", "app_id": "hanauma_bay", "__v": 0, "created_at": "2023-06-20T23:11:09.982Z", "updated_at": "2023-11-14T17:07:26.080Z", "id": "6492320d131dfbc1545a73f8", "local_date_and_time": {"timezone": "GMT-10:00", "timezone_short": "GMT-10", "start_date": "11/16/2023", "start_time": "11:10 AM", "start_day_of_the_week": "Thursday", "end_date": "11/16/2023", "end_time": "11:20 AM", "end_day_of_the_week": "Thursday", "last_ticket_created_at": "Nov 14 at 7:07:26 AM"}}, {"capacity": 35, "tags": [], "is_listed": true, "session_number": 23477, "start_date_time": "2023-11-16T21:20:00.000Z", "end_date_time": "2023-11-16T21:30:00.000Z", "location": {"id": "604bff314dde50e2de52c0e5", "name": "Hanauma Bay Orientation"}, "meta_data": {"tickets_issued": 37, "tickets_available": 0, "tickets_issued_and_invalid": 2, "tickets_issued_and_valid": 35, "last_ticket_created_at": "2023-11-14T17:20:28.411Z"}, "event_id": "607fcb1a9196e149ac206742", "app_id": "hanauma_bay", "__v": 0, "created_at": "2023-06-20T23:11:09.982Z", "updated_at": "2023-11-14T17:20:28.430Z", "id": "6492320d131dfb4d4a5a73f9", "local_date_and_time": {"timezone": "GMT-10:00", "timezone_short": "GMT-10", "start_date": "11/16/2023", "start_time": "11:20 AM", "start_day_of_the_week": "Thursday", "end_date": "11/16/2023", "end_time": "11:30 AM", "end_day_of_the_week": "Thursday", "last_ticket_created_at": "Nov 14 at 7:20:28 AM"}}, {"capacity": 35, "tags": [], "is_listed": true, "session_number": 23478, "start_date_time": "2023-11-16T21:30:00.000Z", "end_date_time": "2023-11-16T21:40:00.000Z", "location": {"id": "604bff314dde50e2de52c0e5", "name": "Hanauma Bay Orientation"}, "meta_data": {"tickets_issued": 41, "tickets_available": 0, "tickets_issued_and_invalid": 6, "tickets_issued_and_valid": 35, "last_ticket_created_at": "2023-11-14T17:18:36.207Z"}, "event_id": "607fcb1a9196e149ac206742", "app_id": "hanauma_bay", "__v": 0, "created_at": "2023-06-20T23:11:09.982Z", "updated_at": "2023-11-14T17:18:36.226Z", "id": "6492320d131dfb10855a73fa", "local_date_and_time": {"timezone": "GMT-10:00", "timezone_short": "GMT-10", "start_date": "11/16/2023", "start_time": "11:30 AM", "start_day_of_the_week": "Thursday", "end_date": "11/16/2023", "end_time": "11:40 AM", "end_day_of_the_week": "Thursday", "last_ticket_created_at": "Nov 14 at 7:18:36 AM"}}, {"capacity": 35, "tags": [], "is_listed": true, "session_number": 23479, "start_date_time": "2023-11-16T21:40:00.000Z", "end_date_time": "2023-11-16T22:00:00.000Z", "location": {"id": "604bff314dde50e2de52c0e5", "name": "Hanauma Bay Orientation"}, "meta_data": {"tickets_issued": 52, "tickets_available": 0, "tickets_issued_and_invalid": 17, "tickets_issued_and_valid": 35, "last_ticket_created_at": "2023-11-14T17:45:13.983Z"}, "event_id": "607fcb1a9196e149ac206742", "app_id": "hanauma_bay", "__v": 0, "created_at": "2023-06-20T23:11:09.982Z", "updated_at": "2023-11-14T17:45:14.008Z", "id": "6492320d131dfb25125a73fb", "local_date_and_time": {"timezone": "GMT-10:00", "timezone_short": "GMT-10", "start_date": "11/16/2023", "start_time": "11:40 AM", "start_day_of_the_week": "Thursday", "end_date": "11/16/2023", "end_time": "12:00 PM", "end_day_of_the_week": "Thursday", "last_ticket_created_at": "Nov 14 at 7:45:13 AM"}}, {"capacity": 35, "tags": [], "is_listed": true, "session_number": 23480, "start_date_time": "2023-11-16T22:00:00.000Z", "end_date_time": "2023-11-16T22:10:00.000Z", "location": {"id": "604bff314dde50e2de52c0e5", "name": "Hanauma Bay Orientation"}, "meta_data": {"tickets_issued": 51, "tickets_available": 0, "tickets_issued_and_invalid": 16, "tickets_issued_and_valid": 35, "last_ticket_created_at": "2023-11-14T17:21:24.642Z"}, "event_id": "607fcb1a9196e149ac206742", "app_id": "hanauma_bay", "__v": 0, "created_at": "2023-06-20T23:11:09.982Z", "updated_at": "2023-11-14T17:21:24.667Z", "id": "6492320d131dfbcfb35a73fc", "local_date_and_time": {"timezone": "GMT-10:00", "timezone_short": "GMT-10", "start_date": "11/16/2023", "start_time": "12:00 PM", "start_day_of_the_week": "Thursday", "end_date": "11/16/2023", "end_time": "12:10 PM", "end_day_of_the_week": "Thursday", "last_ticket_created_at": "Nov 14 at 7:21:24 AM"}}, {"capacity": 35, "tags": [], "is_listed": true, "session_number": 23481, "start_date_time": "2023-11-16T22:10:00.000Z", "end_date_time": "2023-11-16T22:20:00.000Z", "location": {"id": "604bff314dde50e2de52c0e5", "name": "Hanauma Bay Orientation"}, "meta_data": {"tickets_issued": 41, "tickets_available": 0, "tickets_issued_and_invalid": 6, "tickets_issued_and_valid": 35, "last_ticket_created_at": "2023-11-14T17:43:05.948Z"}, "event_id": "607fcb1a9196e149ac206742", "app_id": "hanauma_bay", "__v": 0, "created_at": "2023-06-20T23:11:09.982Z", "updated_at": "2023-11-14T17:43:05.965Z", "id": "6492320d131dfb28c35a73fd", "local_date_and_time": {"timezone": "GMT-10:00", "timezone_short": "GMT-10", "start_date": "11/16/2023", "start_time": "12:10 PM", "start_day_of_the_week": "Thursday", "end_date": "11/16/2023", "end_time": "12:20 PM", "end_day_of_the_week": "Thursday", "last_ticket_created_at": "Nov 14 at 7:43:05 AM"}}, {"capacity": 35, "tags": [], "is_listed": true, "session_number": 23482, "start_date_time": "2023-11-16T22:20:00.000Z", "end_date_time": "2023-11-16T22:30:00.000Z", "location": {"id": "604bff314dde50e2de52c0e5", "name": "Hanauma Bay Orientation"}, "meta_data": {"tickets_issued": 44, "tickets_available": 0, "tickets_issued_and_invalid": 9, "tickets_issued_and_valid": 35, "last_ticket_created_at": "2023-11-14T17:49:16.369Z"}, "event_id": "607fcb1a9196e149ac206742", "app_id": "hanauma_bay", "__v": 0, "created_at": "2023-06-20T23:11:09.982Z", "updated_at": "2023-11-14T17:49:16.400Z", "id": "6492320d131dfb25f25a73fe", "local_date_and_time": {"timezone": "GMT-10:00", "timezone_short": "GMT-10", "start_date": "11/16/2023", "start_time": "12:20 PM", "start_day_of_the_week": "Thursday", "end_date": "11/16/2023", "end_time": "12:30 PM", "end_day_of_the_week": "Thursday", "last_ticket_created_at": "Nov 14 at 7:49:16 AM"}}, {"capacity": 35, "tags": [], "is_listed": true, "session_number": 23483, "start_date_time": "2023-11-16T22:30:00.000Z", "end_date_time": "2023-11-16T22:40:00.000Z", "location": {"id": "604bff314dde50e2de52c0e5", "name": "Hanauma Bay Orientation"}, "meta_data": {"tickets_issued": 57, "tickets_available": 0, "tickets_issued_and_invalid": 22, "tickets_issued_and_valid": 35, "last_ticket_created_at": "2023-11-14T18:33:32.752Z"}, "event_id": "607fcb1a9196e149ac206742", "app_id": "hanauma_bay", "__v": 0, "created_at": "2023-06-20T23:11:09.982Z", "updated_at": "2023-11-14T18:33:32.765Z", "id": "6492320d131dfbf9a75a73ff", "local_date_and_time": {"timezone": "GMT-10:00", "timezone_short": "GMT-10", "start_date": "11/16/2023", "start_time": "12:30 PM", "start_day_of_the_week": "Thursday", "end_date": "11/16/2023", "end_time": "12:40 PM", "end_day_of_the_week": "Thursday", "last_ticket_created_at": "Nov 14 at 8:33:32 AM"}}, {"capacity": 35, "tags": [], "is_listed": true, "session_number": 23484, "start_date_time": "2023-11-16T22:40:00.000Z", "end_date_time": "2023-11-16T23:00:00.000Z", "location": {"id": "604bff314dde50e2de52c0e5", "name": "Hanauma Bay Orientation"}, "meta_data": {"tickets_issued": 46, "tickets_available": 0, "tickets_issued_and_invalid": 11, "tickets_issued_and_valid": 35, "last_ticket_created_at": "2023-11-14T17:52:16.822Z"}, "event_id": "607fcb1a9196e149ac206742", "app_id": "hanauma_bay", "__v": 0, "created_at": "2023-06-20T23:11:09.982Z", "updated_at": "2023-11-14T17:52:16.838Z", "id": "6492320d131dfb15085a7400", "local_date_and_time": {"timezone": "GMT-10:00", "timezone_short": "GMT-10", "start_date": "11/16/2023", "start_time": "12:40 PM", "start_day_of_the_week": "Thursday", "end_date": "11/16/2023", "end_time": "1:00 PM", "end_day_of_the_week": "Thursday", "last_ticket_created_at": "Nov 14 at 7:52:16 AM"}}, {"capacity": 35, "tags": [], "is_listed": true, "session_number": 23485, "start_date_time": "2023-11-16T23:00:00.000Z", "end_date_time": "2023-11-16T23:10:00.000Z", "location": {"id": "604bff314dde50e2de52c0e5", "name": "Hanauma Bay Orientation"}, "meta_data": {"tickets_issued": 37, "tickets_available": 0, "tickets_issued_and_invalid": 2, "tickets_issued_and_valid": 35, "last_ticket_created_at": "2023-11-14T17:51:02.875Z"}, "event_id": "607fcb1a9196e149ac206742", "app_id": "hanauma_bay", "__v": 0, "created_at": "2023-06-20T23:11:09.982Z", "updated_at": "2023-11-14T17:51:02.895Z", "id": "6492320d131dfb585e5a7401", "local_date_and_time": {"timezone": "GMT-10:00", "timezone_short": "GMT-10", "start_date": "11/16/2023", "start_time": "1:00 PM", "start_day_of_the_week": "Thursday", "end_date": "11/16/2023", "end_time": "1:10 PM", "end_day_of_the_week": "Thursday", "last_ticket_created_at": "Nov 14 at 7:51:02 AM"}}, {"capacity": 35, "tags": [], "is_listed": true, "session_number": 23486, "start_date_time": "2023-11-16T23:10:00.000Z", "end_date_time": "2023-11-16T23:20:00.000Z", "location": {"id": "604bff314dde50e2de52c0e5", "name": "Hanauma Bay Orientation"}, "meta_data": {"tickets_issued": 39, "tickets_available": 0, "tickets_issued_and_invalid": 4, "tickets_issued_and_valid": 35, "last_ticket_created_at": "2023-11-14T17:31:42.085Z"}, "event_id": "607fcb1a9196e149ac206742", "app_id": "hanauma_bay", "__v": 0, "created_at": "2023-06-20T23:11:09.983Z", "updated_at": "2023-11-14T17:31:42.104Z", "id": "6492320d131dfb9a8d5a7402", "local_date_and_time": {"timezone": "GMT-10:00", "timezone_short": "GMT-10", "start_date": "11/16/2023", "start_time": "1:10 PM", "start_day_of_the_week": "Thursday", "end_date": "11/16/2023", "end_time": "1:20 PM", "end_day_of_the_week": "Thursday", "last_ticket_created_at": "Nov 14 at 7:31:42 AM"}}, {"capacity": 30, "tags": [], "is_listed": true, "session_number": 23487, "start_date_time": "2023-11-16T23:20:00.000Z", "end_date_time": "2023-11-16T23:30:00.000Z", "location": {"id": "604bff314dde50e2de52c0e5", "name": "Hanauma Bay Orientation"}, "meta_data": {"tickets_issued": 41, "tickets_available": 0, "tickets_issued_and_invalid": 11, "tickets_issued_and_valid": 30, "last_ticket_created_at": "2023-11-14T17:28:57.665Z"}, "event_id": "607fcb1a9196e149ac206742", "app_id": "hanauma_bay", "__v": 0, "created_at": "2023-06-20T23:11:09.983Z", "updated_at": "2023-11-14T17:28:57.696Z", "id": "6492320d131dfb970f5a7403", "local_date_and_time": {"timezone": "GMT-10:00", "timezone_short": "GMT-10", "start_date": "11/16/2023", "start_time": "1:20 PM", "start_day_of_the_week": "Thursday", "end_date": "11/16/2023", "end_time": "1:30 PM", "end_day_of_the_week": "Thursday", "last_ticket_created_at": "Nov 14 at 7:28:57 AM"}}]}}