{"meta": {"page": {"size": 50, "number": 1}, "count": 33}, "data": {"event_sessions": [{"capacity": 15, "tags": [], "is_listed": true, "session_number": 22993, "start_date_time": "2023-10-27T17:00:00.000Z", "end_date_time": "2023-10-27T17:10:00.000Z", "location": {"id": "604bff314dde50e2de52c0e5", "name": "Hanauma Bay Orientation"}, "meta_data": {"tickets_issued": 34, "tickets_available": 0, "tickets_issued_and_invalid": 19, "tickets_issued_and_valid": 15, "last_ticket_created_at": "2023-10-25T18:01:14.714Z"}, "event_id": "607fcb1a9196e149ac206742", "app_id": "hanauma_bay", "__v": 0, "created_at": "2023-06-20T23:11:09.959Z", "updated_at": "2023-10-25T18:01:14.727Z", "id": "6492320c131dfb16285a7215", "local_date_and_time": {"timezone": "GMT-10:00", "timezone_short": "GMT-10", "start_date": "10/27/2023", "start_time": "7:00 AM", "start_day_of_the_week": "Friday", "end_date": "10/27/2023", "end_time": "7:10 AM", "end_day_of_the_week": "Friday", "last_ticket_created_at": "Oct 25 at 8:01:14 AM"}}, {"capacity": 15, "tags": [], "is_listed": true, "session_number": 22994, "start_date_time": "2023-10-27T17:10:00.000Z", "end_date_time": "2023-10-27T17:20:00.000Z", "location": {"id": "604bff314dde50e2de52c0e5", "name": "Hanauma Bay Orientation"}, "meta_data": {"tickets_issued": 16, "tickets_available": 0, "tickets_issued_and_invalid": 1, "tickets_issued_and_valid": 15, "last_ticket_created_at": "2023-10-25T17:05:50.805Z"}, "event_id": "607fcb1a9196e149ac206742", "app_id": "hanauma_bay", "__v": 0, "created_at": "2023-06-20T23:11:09.959Z", "updated_at": "2023-10-25T17:05:50.814Z", "id": "6492320c131dfb2c685a7216", "local_date_and_time": {"timezone": "GMT-10:00", "timezone_short": "GMT-10", "start_date": "10/27/2023", "start_time": "7:10 AM", "start_day_of_the_week": "Friday", "end_date": "10/27/2023", "end_time": "7:20 AM", "end_day_of_the_week": "Friday", "last_ticket_created_at": "Oct 25 at 7:05:50 AM"}}, {"capacity": 15, "tags": [], "is_listed": true, "session_number": 22995, "start_date_time": "2023-10-27T17:20:00.000Z", "end_date_time": "2023-10-27T17:30:00.000Z", "location": {"id": "604bff314dde50e2de52c0e5", "name": "Hanauma Bay Orientation"}, "meta_data": {"tickets_issued": 15, "tickets_available": 0, "tickets_issued_and_invalid": 0, "tickets_issued_and_valid": 15, "last_ticket_created_at": "2023-10-25T17:01:49.426Z"}, "event_id": "607fcb1a9196e149ac206742", "app_id": "hanauma_bay", "__v": 0, "created_at": "2023-06-20T23:11:09.960Z", "updated_at": "2023-10-25T17:01:49.435Z", "id": "6492320c131dfb64c85a7217", "local_date_and_time": {"timezone": "GMT-10:00", "timezone_short": "GMT-10", "start_date": "10/27/2023", "start_time": "7:20 AM", "start_day_of_the_week": "Friday", "end_date": "10/27/2023", "end_time": "7:30 AM", "end_day_of_the_week": "Friday", "last_ticket_created_at": "Oct 25 at 7:01:49 AM"}}, {"capacity": 15, "tags": [], "is_listed": true, "session_number": 22996, "start_date_time": "2023-10-27T17:30:00.000Z", "end_date_time": "2023-10-27T17:40:00.000Z", "location": {"id": "604bff314dde50e2de52c0e5", "name": "Hanauma Bay Orientation"}, "meta_data": {"tickets_issued": 19, "tickets_available": 0, "tickets_issued_and_invalid": 4, "tickets_issued_and_valid": 15, "last_ticket_created_at": "2023-10-25T17:23:22.445Z"}, "event_id": "607fcb1a9196e149ac206742", "app_id": "hanauma_bay", "__v": 0, "created_at": "2023-06-20T23:11:09.960Z", "updated_at": "2023-10-25T17:23:22.456Z", "id": "6492320c131dfb56735a7218", "local_date_and_time": {"timezone": "GMT-10:00", "timezone_short": "GMT-10", "start_date": "10/27/2023", "start_time": "7:30 AM", "start_day_of_the_week": "Friday", "end_date": "10/27/2023", "end_time": "7:40 AM", "end_day_of_the_week": "Friday", "last_ticket_created_at": "Oct 25 at 7:23:22 AM"}}, {"capacity": 15, "tags": [], "is_listed": true, "session_number": 22997, "start_date_time": "2023-10-27T17:40:00.000Z", "end_date_time": "2023-10-27T18:00:00.000Z", "location": {"id": "604bff314dde50e2de52c0e5", "name": "Hanauma Bay Orientation"}, "meta_data": {"tickets_issued": 17, "tickets_available": 0, "tickets_issued_and_invalid": 2, "tickets_issued_and_valid": 15, "last_ticket_created_at": "2023-10-25T17:13:52.129Z"}, "event_id": "607fcb1a9196e149ac206742", "app_id": "hanauma_bay", "__v": 0, "created_at": "2023-06-20T23:11:09.960Z", "updated_at": "2023-10-25T17:13:52.139Z", "id": "6492320c131dfb47ba5a7219", "local_date_and_time": {"timezone": "GMT-10:00", "timezone_short": "GMT-10", "start_date": "10/27/2023", "start_time": "7:40 AM", "start_day_of_the_week": "Friday", "end_date": "10/27/2023", "end_time": "8:00 AM", "end_day_of_the_week": "Friday", "last_ticket_created_at": "Oct 25 at 7:13:52 AM"}}, {"capacity": 35, "tags": [], "is_listed": true, "session_number": 22998, "start_date_time": "2023-10-27T18:00:00.000Z", "end_date_time": "2023-10-27T18:10:00.000Z", "location": {"id": "604bff314dde50e2de52c0e5", "name": "Hanauma Bay Orientation"}, "meta_data": {"tickets_issued": 49, "tickets_available": 0, "tickets_issued_and_invalid": 14, "tickets_issued_and_valid": 35, "last_ticket_created_at": "2023-10-25T17:19:07.732Z"}, "event_id": "607fcb1a9196e149ac206742", "app_id": "hanauma_bay", "__v": 0, "created_at": "2023-06-20T23:11:09.960Z", "updated_at": "2023-10-25T17:19:07.762Z", "id": "6492320c131dfb88e95a721a", "local_date_and_time": {"timezone": "GMT-10:00", "timezone_short": "GMT-10", "start_date": "10/27/2023", "start_time": "8:00 AM", "start_day_of_the_week": "Friday", "end_date": "10/27/2023", "end_time": "8:10 AM", "end_day_of_the_week": "Friday", "last_ticket_created_at": "Oct 25 at 7:19:07 AM"}}, {"capacity": 35, "tags": [], "is_listed": true, "session_number": 22999, "start_date_time": "2023-10-27T18:10:00.000Z", "end_date_time": "2023-10-27T18:20:00.000Z", "location": {"id": "604bff314dde50e2de52c0e5", "name": "Hanauma Bay Orientation"}, "meta_data": {"tickets_issued": 45, "tickets_available": 0, "tickets_issued_and_invalid": 10, "tickets_issued_and_valid": 35, "last_ticket_created_at": "2023-10-25T17:45:18.491Z"}, "event_id": "607fcb1a9196e149ac206742", "app_id": "hanauma_bay", "__v": 0, "created_at": "2023-06-20T23:11:09.960Z", "updated_at": "2023-10-25T17:45:18.509Z", "id": "6492320c131dfb8aa85a721b", "local_date_and_time": {"timezone": "GMT-10:00", "timezone_short": "GMT-10", "start_date": "10/27/2023", "start_time": "8:10 AM", "start_day_of_the_week": "Friday", "end_date": "10/27/2023", "end_time": "8:20 AM", "end_day_of_the_week": "Friday", "last_ticket_created_at": "Oct 25 at 7:45:18 AM"}}, {"capacity": 35, "tags": [], "is_listed": true, "session_number": 23000, "start_date_time": "2023-10-27T18:20:00.000Z", "end_date_time": "2023-10-27T18:30:00.000Z", "location": {"id": "604bff314dde50e2de52c0e5", "name": "Hanauma Bay Orientation"}, "meta_data": {"tickets_issued": 51, "tickets_available": 0, "tickets_issued_and_invalid": 16, "tickets_issued_and_valid": 35, "last_ticket_created_at": "2023-10-25T17:43:31.448Z"}, "event_id": "607fcb1a9196e149ac206742", "app_id": "hanauma_bay", "__v": 0, "created_at": "2023-06-20T23:11:09.960Z", "updated_at": "2023-10-25T17:43:31.470Z", "id": "6492320c131dfb0ad65a721c", "local_date_and_time": {"timezone": "GMT-10:00", "timezone_short": "GMT-10", "start_date": "10/27/2023", "start_time": "8:20 AM", "start_day_of_the_week": "Friday", "end_date": "10/27/2023", "end_time": "8:30 AM", "end_day_of_the_week": "Friday", "last_ticket_created_at": "Oct 25 at 7:43:31 AM"}}, {"capacity": 35, "tags": [], "is_listed": true, "session_number": 23001, "start_date_time": "2023-10-27T18:30:00.000Z", "end_date_time": "2023-10-27T18:40:00.000Z", "location": {"id": "604bff314dde50e2de52c0e5", "name": "Hanauma Bay Orientation"}, "meta_data": {"tickets_issued": 37, "tickets_available": 0, "tickets_issued_and_invalid": 2, "tickets_issued_and_valid": 35, "last_ticket_created_at": "2023-10-25T17:07:33.177Z"}, "event_id": "607fcb1a9196e149ac206742", "app_id": "hanauma_bay", "__v": 0, "created_at": "2023-06-20T23:11:09.960Z", "updated_at": "2023-10-25T17:07:33.197Z", "id": "6492320c131dfb5ed15a721d", "local_date_and_time": {"timezone": "GMT-10:00", "timezone_short": "GMT-10", "start_date": "10/27/2023", "start_time": "8:30 AM", "start_day_of_the_week": "Friday", "end_date": "10/27/2023", "end_time": "8:40 AM", "end_day_of_the_week": "Friday", "last_ticket_created_at": "Oct 25 at 7:07:33 AM"}}, {"capacity": 35, "tags": [], "is_listed": true, "session_number": 23002, "start_date_time": "2023-10-27T18:40:00.000Z", "end_date_time": "2023-10-27T19:00:00.000Z", "location": {"id": "604bff314dde50e2de52c0e5", "name": "Hanauma Bay Orientation"}, "meta_data": {"tickets_issued": 55, "tickets_available": 0, "tickets_issued_and_invalid": 20, "tickets_issued_and_valid": 35, "last_ticket_created_at": "2023-10-25T18:06:17.461Z"}, "event_id": "607fcb1a9196e149ac206742", "app_id": "hanauma_bay", "__v": 0, "created_at": "2023-06-20T23:11:09.960Z", "updated_at": "2023-10-25T18:06:17.481Z", "id": "6492320c131dfb77405a721e", "local_date_and_time": {"timezone": "GMT-10:00", "timezone_short": "GMT-10", "start_date": "10/27/2023", "start_time": "8:40 AM", "start_day_of_the_week": "Friday", "end_date": "10/27/2023", "end_time": "9:00 AM", "end_day_of_the_week": "Friday", "last_ticket_created_at": "Oct 25 at 8:06:17 AM"}}, {"capacity": 35, "tags": [], "is_listed": true, "session_number": 23003, "start_date_time": "2023-10-27T19:00:00.000Z", "end_date_time": "2023-10-27T19:10:00.000Z", "location": {"id": "604bff314dde50e2de52c0e5", "name": "Hanauma Bay Orientation"}, "meta_data": {"tickets_issued": 51, "tickets_available": 0, "tickets_issued_and_invalid": 16, "tickets_issued_and_valid": 35, "last_ticket_created_at": "2023-10-25T17:36:10.785Z"}, "event_id": "607fcb1a9196e149ac206742", "app_id": "hanauma_bay", "__v": 0, "created_at": "2023-06-20T23:11:09.960Z", "updated_at": "2023-10-25T17:36:10.804Z", "id": "6492320c131dfb77e25a721f", "local_date_and_time": {"timezone": "GMT-10:00", "timezone_short": "GMT-10", "start_date": "10/27/2023", "start_time": "9:00 AM", "start_day_of_the_week": "Friday", "end_date": "10/27/2023", "end_time": "9:10 AM", "end_day_of_the_week": "Friday", "last_ticket_created_at": "Oct 25 at 7:36:10 AM"}}, {"capacity": 35, "tags": [], "is_listed": true, "session_number": 23004, "start_date_time": "2023-10-27T19:10:00.000Z", "end_date_time": "2023-10-27T19:20:00.000Z", "location": {"id": "604bff314dde50e2de52c0e5", "name": "Hanauma Bay Orientation"}, "meta_data": {"tickets_issued": 52, "tickets_available": 0, "tickets_issued_and_invalid": 17, "tickets_issued_and_valid": 35, "last_ticket_created_at": "2023-10-25T17:45:58.729Z"}, "event_id": "607fcb1a9196e149ac206742", "app_id": "hanauma_bay", "__v": 0, "created_at": "2023-06-20T23:11:09.960Z", "updated_at": "2023-10-25T18:12:26.774Z", "id": "6492320c131dfbe2fe5a7220", "local_date_and_time": {"timezone": "GMT-10:00", "timezone_short": "GMT-10", "start_date": "10/27/2023", "start_time": "9:10 AM", "start_day_of_the_week": "Friday", "end_date": "10/27/2023", "end_time": "9:20 AM", "end_day_of_the_week": "Friday", "last_ticket_created_at": "Oct 25 at 7:45:58 AM"}}, {"capacity": 35, "tags": [], "is_listed": true, "session_number": 23005, "start_date_time": "2023-10-27T19:20:00.000Z", "end_date_time": "2023-10-27T19:30:00.000Z", "location": {"id": "604bff314dde50e2de52c0e5", "name": "Hanauma Bay Orientation"}, "meta_data": {"tickets_issued": 38, "tickets_available": 0, "tickets_issued_and_invalid": 3, "tickets_issued_and_valid": 35, "last_ticket_created_at": "2023-10-25T17:31:24.833Z"}, "event_id": "607fcb1a9196e149ac206742", "app_id": "hanauma_bay", "__v": 0, "created_at": "2023-06-20T23:11:09.960Z", "updated_at": "2023-10-25T17:31:24.852Z", "id": "6492320c131dfb63255a7221", "local_date_and_time": {"timezone": "GMT-10:00", "timezone_short": "GMT-10", "start_date": "10/27/2023", "start_time": "9:20 AM", "start_day_of_the_week": "Friday", "end_date": "10/27/2023", "end_time": "9:30 AM", "end_day_of_the_week": "Friday", "last_ticket_created_at": "Oct 25 at 7:31:24 AM"}}, {"capacity": 35, "tags": [], "is_listed": true, "session_number": 23006, "start_date_time": "2023-10-27T19:30:00.000Z", "end_date_time": "2023-10-27T19:40:00.000Z", "location": {"id": "604bff314dde50e2de52c0e5", "name": "Hanauma Bay Orientation"}, "meta_data": {"tickets_issued": 35, "tickets_available": 0, "tickets_issued_and_invalid": 0, "tickets_issued_and_valid": 35, "last_ticket_created_at": "2023-10-25T17:02:56.422Z"}, "event_id": "607fcb1a9196e149ac206742", "app_id": "hanauma_bay", "__v": 0, "created_at": "2023-06-20T23:11:09.960Z", "updated_at": "2023-10-25T17:02:56.434Z", "id": "6492320c131dfb514c5a7222", "local_date_and_time": {"timezone": "GMT-10:00", "timezone_short": "GMT-10", "start_date": "10/27/2023", "start_time": "9:30 AM", "start_day_of_the_week": "Friday", "end_date": "10/27/2023", "end_time": "9:40 AM", "end_day_of_the_week": "Friday", "last_ticket_created_at": "Oct 25 at 7:02:56 AM"}}, {"capacity": 35, "tags": [], "is_listed": true, "session_number": 23007, "start_date_time": "2023-10-27T19:40:00.000Z", "end_date_time": "2023-10-27T20:00:00.000Z", "location": {"id": "604bff314dde50e2de52c0e5", "name": "Hanauma Bay Orientation"}, "meta_data": {"tickets_issued": 62, "tickets_available": 0, "tickets_issued_and_invalid": 27, "tickets_issued_and_valid": 35, "last_ticket_created_at": "2023-10-25T17:35:07.345Z"}, "event_id": "607fcb1a9196e149ac206742", "app_id": "hanauma_bay", "__v": 0, "created_at": "2023-06-20T23:11:09.960Z", "updated_at": "2023-10-25T17:35:07.365Z", "id": "6492320c131dfbb0325a7223", "local_date_and_time": {"timezone": "GMT-10:00", "timezone_short": "GMT-10", "start_date": "10/27/2023", "start_time": "9:40 AM", "start_day_of_the_week": "Friday", "end_date": "10/27/2023", "end_time": "10:00 AM", "end_day_of_the_week": "Friday", "last_ticket_created_at": "Oct 25 at 7:35:07 AM"}}, {"capacity": 35, "tags": [], "is_listed": true, "session_number": 23008, "start_date_time": "2023-10-27T20:00:00.000Z", "end_date_time": "2023-10-27T20:10:00.000Z", "location": {"id": "604bff314dde50e2de52c0e5", "name": "Hanauma Bay Orientation"}, "meta_data": {"tickets_issued": 35, "tickets_available": 0, "tickets_issued_and_invalid": 0, "tickets_issued_and_valid": 35, "last_ticket_created_at": "2023-10-25T17:01:20.908Z"}, "event_id": "607fcb1a9196e149ac206742", "app_id": "hanauma_bay", "__v": 0, "created_at": "2023-06-20T23:11:09.960Z", "updated_at": "2023-10-25T17:01:20.920Z", "id": "6492320c131dfb8fb65a7224", "local_date_and_time": {"timezone": "GMT-10:00", "timezone_short": "GMT-10", "start_date": "10/27/2023", "start_time": "10:00 AM", "start_day_of_the_week": "Friday", "end_date": "10/27/2023", "end_time": "10:10 AM", "end_day_of_the_week": "Friday", "last_ticket_created_at": "Oct 25 at 7:01:20 AM"}}, {"capacity": 35, "tags": [], "is_listed": true, "session_number": 23009, "start_date_time": "2023-10-27T20:10:00.000Z", "end_date_time": "2023-10-27T20:20:00.000Z", "location": {"id": "604bff314dde50e2de52c0e5", "name": "Hanauma Bay Orientation"}, "meta_data": {"tickets_issued": 44, "tickets_available": 0, "tickets_issued_and_invalid": 9, "tickets_issued_and_valid": 35, "last_ticket_created_at": "2023-10-25T17:20:16.589Z"}, "event_id": "607fcb1a9196e149ac206742", "app_id": "hanauma_bay", "__v": 0, "created_at": "2023-06-20T23:11:09.960Z", "updated_at": "2023-10-25T17:20:16.605Z", "id": "6492320c131dfbda455a7225", "local_date_and_time": {"timezone": "GMT-10:00", "timezone_short": "GMT-10", "start_date": "10/27/2023", "start_time": "10:10 AM", "start_day_of_the_week": "Friday", "end_date": "10/27/2023", "end_time": "10:20 AM", "end_day_of_the_week": "Friday", "last_ticket_created_at": "Oct 25 at 7:20:16 AM"}}, {"capacity": 35, "tags": [], "is_listed": true, "session_number": 23010, "start_date_time": "2023-10-27T20:20:00.000Z", "end_date_time": "2023-10-27T20:30:00.000Z", "location": {"id": "604bff314dde50e2de52c0e5", "name": "Hanauma Bay Orientation"}, "meta_data": {"tickets_issued": 59, "tickets_available": 0, "tickets_issued_and_invalid": 24, "tickets_issued_and_valid": 35, "last_ticket_created_at": "2023-10-25T17:36:11.476Z"}, "event_id": "607fcb1a9196e149ac206742", "app_id": "hanauma_bay", "__v": 0, "created_at": "2023-06-20T23:11:09.960Z", "updated_at": "2023-10-25T17:36:11.494Z", "id": "6492320c131dfb2c295a7226", "local_date_and_time": {"timezone": "GMT-10:00", "timezone_short": "GMT-10", "start_date": "10/27/2023", "start_time": "10:20 AM", "start_day_of_the_week": "Friday", "end_date": "10/27/2023", "end_time": "10:30 AM", "end_day_of_the_week": "Friday", "last_ticket_created_at": "Oct 25 at 7:36:11 AM"}}, {"capacity": 35, "tags": [], "is_listed": true, "session_number": 23011, "start_date_time": "2023-10-27T20:30:00.000Z", "end_date_time": "2023-10-27T20:40:00.000Z", "location": {"id": "604bff314dde50e2de52c0e5", "name": "Hanauma Bay Orientation"}, "meta_data": {"tickets_issued": 40, "tickets_available": 0, "tickets_issued_and_invalid": 5, "tickets_issued_and_valid": 35, "last_ticket_created_at": "2023-10-25T17:26:42.408Z"}, "event_id": "607fcb1a9196e149ac206742", "app_id": "hanauma_bay", "__v": 0, "created_at": "2023-06-20T23:11:09.960Z", "updated_at": "2023-10-25T17:26:42.420Z", "id": "6492320c131dfb4ffd5a7227", "local_date_and_time": {"timezone": "GMT-10:00", "timezone_short": "GMT-10", "start_date": "10/27/2023", "start_time": "10:30 AM", "start_day_of_the_week": "Friday", "end_date": "10/27/2023", "end_time": "10:40 AM", "end_day_of_the_week": "Friday", "last_ticket_created_at": "Oct 25 at 7:26:42 AM"}}, {"capacity": 35, "tags": [], "is_listed": true, "session_number": 23012, "start_date_time": "2023-10-27T20:40:00.000Z", "end_date_time": "2023-10-27T21:00:00.000Z", "location": {"id": "604bff314dde50e2de52c0e5", "name": "Hanauma Bay Orientation"}, "meta_data": {"tickets_issued": 37, "tickets_available": 0, "tickets_issued_and_invalid": 2, "tickets_issued_and_valid": 35, "last_ticket_created_at": "2023-10-25T17:06:21.170Z"}, "event_id": "607fcb1a9196e149ac206742", "app_id": "hanauma_bay", "__v": 0, "created_at": "2023-06-20T23:11:09.960Z", "updated_at": "2023-10-25T17:06:21.189Z", "id": "6492320c131dfbd3765a7228", "local_date_and_time": {"timezone": "GMT-10:00", "timezone_short": "GMT-10", "start_date": "10/27/2023", "start_time": "10:40 AM", "start_day_of_the_week": "Friday", "end_date": "10/27/2023", "end_time": "11:00 AM", "end_day_of_the_week": "Friday", "last_ticket_created_at": "Oct 25 at 7:06:21 AM"}}, {"capacity": 35, "tags": [], "is_listed": true, "session_number": 23013, "start_date_time": "2023-10-27T21:00:00.000Z", "end_date_time": "2023-10-27T21:10:00.000Z", "location": {"id": "604bff314dde50e2de52c0e5", "name": "Hanauma Bay Orientation"}, "meta_data": {"tickets_issued": 37, "tickets_available": 0, "tickets_issued_and_invalid": 2, "tickets_issued_and_valid": 35, "last_ticket_created_at": "2023-10-25T17:05:40.157Z"}, "event_id": "607fcb1a9196e149ac206742", "app_id": "hanauma_bay", "__v": 0, "created_at": "2023-06-20T23:11:09.960Z", "updated_at": "2023-10-25T17:05:40.175Z", "id": "6492320c131dfb2df05a7229", "local_date_and_time": {"timezone": "GMT-10:00", "timezone_short": "GMT-10", "start_date": "10/27/2023", "start_time": "11:00 AM", "start_day_of_the_week": "Friday", "end_date": "10/27/2023", "end_time": "11:10 AM", "end_day_of_the_week": "Friday", "last_ticket_created_at": "Oct 25 at 7:05:40 AM"}}, {"capacity": 35, "tags": [], "is_listed": true, "session_number": 23014, "start_date_time": "2023-10-27T21:10:00.000Z", "end_date_time": "2023-10-27T21:20:00.000Z", "location": {"id": "604bff314dde50e2de52c0e5", "name": "Hanauma Bay Orientation"}, "meta_data": {"tickets_issued": 37, "tickets_available": 0, "tickets_issued_and_invalid": 2, "tickets_issued_and_valid": 35, "last_ticket_created_at": "2023-10-25T17:21:43.959Z"}, "event_id": "607fcb1a9196e149ac206742", "app_id": "hanauma_bay", "__v": 0, "created_at": "2023-06-20T23:11:09.960Z", "updated_at": "2023-10-25T17:21:43.973Z", "id": "6492320c131dfb082b5a722a", "local_date_and_time": {"timezone": "GMT-10:00", "timezone_short": "GMT-10", "start_date": "10/27/2023", "start_time": "11:10 AM", "start_day_of_the_week": "Friday", "end_date": "10/27/2023", "end_time": "11:20 AM", "end_day_of_the_week": "Friday", "last_ticket_created_at": "Oct 25 at 7:21:43 AM"}}, {"capacity": 35, "tags": [], "is_listed": true, "session_number": 23015, "start_date_time": "2023-10-27T21:20:00.000Z", "end_date_time": "2023-10-27T21:30:00.000Z", "location": {"id": "604bff314dde50e2de52c0e5", "name": "Hanauma Bay Orientation"}, "meta_data": {"tickets_issued": 35, "tickets_available": 0, "tickets_issued_and_invalid": 0, "tickets_issued_and_valid": 35, "last_ticket_created_at": "2023-10-25T17:06:17.303Z"}, "event_id": "607fcb1a9196e149ac206742", "app_id": "hanauma_bay", "__v": 0, "created_at": "2023-06-20T23:11:09.960Z", "updated_at": "2023-10-25T17:06:17.321Z", "id": "6492320c131dfb45215a722b", "local_date_and_time": {"timezone": "GMT-10:00", "timezone_short": "GMT-10", "start_date": "10/27/2023", "start_time": "11:20 AM", "start_day_of_the_week": "Friday", "end_date": "10/27/2023", "end_time": "11:30 AM", "end_day_of_the_week": "Friday", "last_ticket_created_at": "Oct 25 at 7:06:17 AM"}}, {"capacity": 35, "tags": [], "is_listed": true, "session_number": 23016, "start_date_time": "2023-10-27T21:30:00.000Z", "end_date_time": "2023-10-27T21:40:00.000Z", "location": {"id": "604bff314dde50e2de52c0e5", "name": "Hanauma Bay Orientation"}, "meta_data": {"tickets_issued": 53, "tickets_available": 0, "tickets_issued_and_invalid": 18, "tickets_issued_and_valid": 35, "last_ticket_created_at": "2023-10-25T17:20:41.213Z"}, "event_id": "607fcb1a9196e149ac206742", "app_id": "hanauma_bay", "__v": 0, "created_at": "2023-06-20T23:11:09.960Z", "updated_at": "2023-10-25T17:20:41.232Z", "id": "6492320c131dfb5d4c5a722c", "local_date_and_time": {"timezone": "GMT-10:00", "timezone_short": "GMT-10", "start_date": "10/27/2023", "start_time": "11:30 AM", "start_day_of_the_week": "Friday", "end_date": "10/27/2023", "end_time": "11:40 AM", "end_day_of_the_week": "Friday", "last_ticket_created_at": "Oct 25 at 7:20:41 AM"}}, {"capacity": 35, "tags": [], "is_listed": true, "session_number": 23017, "start_date_time": "2023-10-27T21:40:00.000Z", "end_date_time": "2023-10-27T22:00:00.000Z", "location": {"id": "604bff314dde50e2de52c0e5", "name": "Hanauma Bay Orientation"}, "meta_data": {"tickets_issued": 39, "tickets_available": 0, "tickets_issued_and_invalid": 4, "tickets_issued_and_valid": 35, "last_ticket_created_at": "2023-10-25T17:18:47.755Z"}, "event_id": "607fcb1a9196e149ac206742", "app_id": "hanauma_bay", "__v": 0, "created_at": "2023-06-20T23:11:09.960Z", "updated_at": "2023-10-25T17:18:47.772Z", "id": "6492320c131dfbfa6e5a722d", "local_date_and_time": {"timezone": "GMT-10:00", "timezone_short": "GMT-10", "start_date": "10/27/2023", "start_time": "11:40 AM", "start_day_of_the_week": "Friday", "end_date": "10/27/2023", "end_time": "12:00 PM", "end_day_of_the_week": "Friday", "last_ticket_created_at": "Oct 25 at 7:18:47 AM"}}, {"capacity": 35, "tags": [], "is_listed": true, "session_number": 23018, "start_date_time": "2023-10-27T22:00:00.000Z", "end_date_time": "2023-10-27T22:10:00.000Z", "location": {"id": "604bff314dde50e2de52c0e5", "name": "Hanauma Bay Orientation"}, "meta_data": {"tickets_issued": 45, "tickets_available": 0, "tickets_issued_and_invalid": 10, "tickets_issued_and_valid": 35, "last_ticket_created_at": "2023-10-25T17:18:04.837Z"}, "event_id": "607fcb1a9196e149ac206742", "app_id": "hanauma_bay", "__v": 0, "created_at": "2023-06-20T23:11:09.960Z", "updated_at": "2023-10-25T17:18:04.858Z", "id": "6492320c131dfb10385a722e", "local_date_and_time": {"timezone": "GMT-10:00", "timezone_short": "GMT-10", "start_date": "10/27/2023", "start_time": "12:00 PM", "start_day_of_the_week": "Friday", "end_date": "10/27/2023", "end_time": "12:10 PM", "end_day_of_the_week": "Friday", "last_ticket_created_at": "Oct 25 at 7:18:04 AM"}}, {"capacity": 35, "tags": [], "is_listed": true, "session_number": 23019, "start_date_time": "2023-10-27T22:10:00.000Z", "end_date_time": "2023-10-27T22:20:00.000Z", "location": {"id": "604bff314dde50e2de52c0e5", "name": "Hanauma Bay Orientation"}, "meta_data": {"tickets_issued": 47, "tickets_available": 0, "tickets_issued_and_invalid": 12, "tickets_issued_and_valid": 35, "last_ticket_created_at": "2023-10-25T17:25:33.026Z"}, "event_id": "607fcb1a9196e149ac206742", "app_id": "hanauma_bay", "__v": 0, "created_at": "2023-06-20T23:11:09.960Z", "updated_at": "2023-10-25T17:25:33.038Z", "id": "6492320c131dfb11f75a722f", "local_date_and_time": {"timezone": "GMT-10:00", "timezone_short": "GMT-10", "start_date": "10/27/2023", "start_time": "12:10 PM", "start_day_of_the_week": "Friday", "end_date": "10/27/2023", "end_time": "12:20 PM", "end_day_of_the_week": "Friday", "last_ticket_created_at": "Oct 25 at 7:25:33 AM"}}, {"capacity": 35, "tags": [], "is_listed": true, "session_number": 23020, "start_date_time": "2023-10-27T22:20:00.000Z", "end_date_time": "2023-10-27T22:30:00.000Z", "location": {"id": "604bff314dde50e2de52c0e5", "name": "Hanauma Bay Orientation"}, "meta_data": {"tickets_issued": 57, "tickets_available": 0, "tickets_issued_and_invalid": 22, "tickets_issued_and_valid": 35, "last_ticket_created_at": "2023-10-25T18:21:42.936Z"}, "event_id": "607fcb1a9196e149ac206742", "app_id": "hanauma_bay", "__v": 0, "created_at": "2023-06-20T23:11:09.961Z", "updated_at": "2023-10-25T18:21:42.952Z", "id": "6492320c131dfbc4d45a7230", "local_date_and_time": {"timezone": "GMT-10:00", "timezone_short": "GMT-10", "start_date": "10/27/2023", "start_time": "12:20 PM", "start_day_of_the_week": "Friday", "end_date": "10/27/2023", "end_time": "12:30 PM", "end_day_of_the_week": "Friday", "last_ticket_created_at": "Oct 25 at 8:21:42 AM"}}, {"capacity": 35, "tags": [], "is_listed": true, "session_number": 23021, "start_date_time": "2023-10-27T22:30:00.000Z", "end_date_time": "2023-10-27T22:40:00.000Z", "location": {"id": "604bff314dde50e2de52c0e5", "name": "Hanauma Bay Orientation"}, "meta_data": {"tickets_issued": 46, "tickets_available": 0, "tickets_issued_and_invalid": 11, "tickets_issued_and_valid": 35, "last_ticket_created_at": "2023-10-25T17:29:05.765Z"}, "event_id": "607fcb1a9196e149ac206742", "app_id": "hanauma_bay", "__v": 0, "created_at": "2023-06-20T23:11:09.961Z", "updated_at": "2023-10-25T17:29:05.786Z", "id": "6492320c131dfbd7c25a7231", "local_date_and_time": {"timezone": "GMT-10:00", "timezone_short": "GMT-10", "start_date": "10/27/2023", "start_time": "12:30 PM", "start_day_of_the_week": "Friday", "end_date": "10/27/2023", "end_time": "12:40 PM", "end_day_of_the_week": "Friday", "last_ticket_created_at": "Oct 25 at 7:29:05 AM"}}, {"capacity": 35, "tags": [], "is_listed": true, "session_number": 23022, "start_date_time": "2023-10-27T22:40:00.000Z", "end_date_time": "2023-10-27T23:00:00.000Z", "location": {"id": "604bff314dde50e2de52c0e5", "name": "Hanauma Bay Orientation"}, "meta_data": {"tickets_issued": 54, "tickets_available": 0, "tickets_issued_and_invalid": 19, "tickets_issued_and_valid": 35, "last_ticket_created_at": "2023-10-25T17:31:39.278Z"}, "event_id": "607fcb1a9196e149ac206742", "app_id": "hanauma_bay", "__v": 0, "created_at": "2023-06-20T23:11:09.961Z", "updated_at": "2023-10-25T17:31:39.322Z", "id": "6492320c131dfbdaa75a7232", "local_date_and_time": {"timezone": "GMT-10:00", "timezone_short": "GMT-10", "start_date": "10/27/2023", "start_time": "12:40 PM", "start_day_of_the_week": "Friday", "end_date": "10/27/2023", "end_time": "1:00 PM", "end_day_of_the_week": "Friday", "last_ticket_created_at": "Oct 25 at 7:31:39 AM"}}, {"capacity": 35, "tags": [], "is_listed": true, "session_number": 23023, "start_date_time": "2023-10-27T23:00:00.000Z", "end_date_time": "2023-10-27T23:10:00.000Z", "location": {"id": "604bff314dde50e2de52c0e5", "name": "Hanauma Bay Orientation"}, "meta_data": {"tickets_issued": 37, "tickets_available": 0, "tickets_issued_and_invalid": 2, "tickets_issued_and_valid": 35, "last_ticket_created_at": "2023-10-25T17:46:31.598Z"}, "event_id": "607fcb1a9196e149ac206742", "app_id": "hanauma_bay", "__v": 0, "created_at": "2023-06-20T23:11:09.961Z", "updated_at": "2023-10-25T17:46:31.612Z", "id": "6492320c131dfb6ddc5a7233", "local_date_and_time": {"timezone": "GMT-10:00", "timezone_short": "GMT-10", "start_date": "10/27/2023", "start_time": "1:00 PM", "start_day_of_the_week": "Friday", "end_date": "10/27/2023", "end_time": "1:10 PM", "end_day_of_the_week": "Friday", "last_ticket_created_at": "Oct 25 at 7:46:31 AM"}}, {"capacity": 35, "tags": [], "is_listed": true, "session_number": 23024, "start_date_time": "2023-10-27T23:10:00.000Z", "end_date_time": "2023-10-27T23:20:00.000Z", "location": {"id": "604bff314dde50e2de52c0e5", "name": "Hanauma Bay Orientation"}, "meta_data": {"tickets_issued": 47, "tickets_available": 0, "tickets_issued_and_invalid": 12, "tickets_issued_and_valid": 35, "last_ticket_created_at": "2023-10-25T18:26:21.403Z"}, "event_id": "607fcb1a9196e149ac206742", "app_id": "hanauma_bay", "__v": 0, "created_at": "2023-06-20T23:11:09.961Z", "updated_at": "2023-10-25T18:26:21.426Z", "id": "6492320c131dfb76b95a7234", "local_date_and_time": {"timezone": "GMT-10:00", "timezone_short": "GMT-10", "start_date": "10/27/2023", "start_time": "1:10 PM", "start_day_of_the_week": "Friday", "end_date": "10/27/2023", "end_time": "1:20 PM", "end_day_of_the_week": "Friday", "last_ticket_created_at": "Oct 25 at 8:26:21 AM"}}, {"capacity": 30, "tags": [], "is_listed": true, "session_number": 23025, "start_date_time": "2023-10-27T23:20:00.000Z", "end_date_time": "2023-10-27T23:30:00.000Z", "location": {"id": "604bff314dde50e2de52c0e5", "name": "Hanauma Bay Orientation"}, "meta_data": {"tickets_issued": 42, "tickets_available": 0, "tickets_issued_and_invalid": 12, "tickets_issued_and_valid": 30, "last_ticket_created_at": "2023-10-25T18:25:46.576Z"}, "event_id": "607fcb1a9196e149ac206742", "app_id": "hanauma_bay", "__v": 0, "created_at": "2023-06-20T23:11:09.961Z", "updated_at": "2023-10-25T18:25:46.606Z", "id": "6492320c131dfb685a5a7235", "local_date_and_time": {"timezone": "GMT-10:00", "timezone_short": "GMT-10", "start_date": "10/27/2023", "start_time": "1:20 PM", "start_day_of_the_week": "Friday", "end_date": "10/27/2023", "end_time": "1:30 PM", "end_day_of_the_week": "Friday", "last_ticket_created_at": "Oct 25 at 8:25:46 AM"}}]}}