{"meta": {"page": {"size": 50, "number": 1}, "count": 33}, "data": {"event_sessions": [{"event_id": "607fcb1a9196e149ac206742", "session_number": 34906, "app_id": "hanauma_bay", "location": {"id": "604bff314dde50e2de52c0e5", "name": "Hanauma Bay Orientation"}, "capacity": 15, "start_date_time": "2025-03-16T17:00:00.000Z", "end_date_time": "2025-03-16T17:10:00.000Z", "tags": [], "is_listed": true, "meta_data": {"tickets_issued": 29, "tickets_available": 0, "tickets_issued_and_invalid": 14, "tickets_issued_and_valid": 15, "last_ticket_created_at": "2025-03-14T17:04:30.175Z"}, "__v": 0, "created_at": "2024-12-16T20:16:10.571Z", "updated_at": "2025-03-14T17:04:30.187Z", "id": "67608a88e4a20e123832056d", "local_date_and_time": {"timezone": "GMT-10:00", "timezone_short": "GMT-10", "start_date": "3/16/2025", "start_time": "7:00 AM", "start_day_of_the_week": "Sunday", "end_date": "3/16/2025", "end_time": "7:10 AM", "end_day_of_the_week": "Sunday", "last_ticket_created_at": "Mar 14 at 7:04:30 AM"}}, {"event_id": "607fcb1a9196e149ac206742", "session_number": 34907, "app_id": "hanauma_bay", "location": {"id": "604bff314dde50e2de52c0e5", "name": "Hanauma Bay Orientation"}, "capacity": 15, "start_date_time": "2025-03-16T17:10:00.000Z", "end_date_time": "2025-03-16T17:20:00.000Z", "tags": [], "is_listed": true, "meta_data": {"tickets_issued": 21, "tickets_available": 0, "tickets_issued_and_invalid": 6, "tickets_issued_and_valid": 15, "last_ticket_created_at": "2025-03-14T17:02:30.285Z"}, "__v": 0, "created_at": "2024-12-16T20:16:10.571Z", "updated_at": "2025-03-14T17:02:30.291Z", "id": "67608a88e4a20e123832056e", "local_date_and_time": {"timezone": "GMT-10:00", "timezone_short": "GMT-10", "start_date": "3/16/2025", "start_time": "7:10 AM", "start_day_of_the_week": "Sunday", "end_date": "3/16/2025", "end_time": "7:20 AM", "end_day_of_the_week": "Sunday", "last_ticket_created_at": "Mar 14 at 7:02:30 AM"}}, {"event_id": "607fcb1a9196e149ac206742", "session_number": 34908, "app_id": "hanauma_bay", "location": {"id": "604bff314dde50e2de52c0e5", "name": "Hanauma Bay Orientation"}, "capacity": 15, "start_date_time": "2025-03-16T17:20:00.000Z", "end_date_time": "2025-03-16T17:30:00.000Z", "tags": [], "is_listed": true, "meta_data": {"tickets_issued": 26, "tickets_available": 0, "tickets_issued_and_invalid": 11, "tickets_issued_and_valid": 15, "last_ticket_created_at": "2025-03-14T17:24:04.397Z"}, "__v": 0, "created_at": "2024-12-16T20:16:10.571Z", "updated_at": "2025-03-14T17:24:04.411Z", "id": "67608a88e4a20e123832056f", "local_date_and_time": {"timezone": "GMT-10:00", "timezone_short": "GMT-10", "start_date": "3/16/2025", "start_time": "7:20 AM", "start_day_of_the_week": "Sunday", "end_date": "3/16/2025", "end_time": "7:30 AM", "end_day_of_the_week": "Sunday", "last_ticket_created_at": "Mar 14 at 7:24:04 AM"}}, {"event_id": "607fcb1a9196e149ac206742", "session_number": 34909, "app_id": "hanauma_bay", "location": {"id": "604bff314dde50e2de52c0e5", "name": "Hanauma Bay Orientation"}, "capacity": 15, "start_date_time": "2025-03-16T17:30:00.000Z", "end_date_time": "2025-03-16T17:40:00.000Z", "tags": [], "is_listed": true, "meta_data": {"tickets_issued": 17, "tickets_available": 0, "tickets_issued_and_invalid": 2, "tickets_issued_and_valid": 15, "last_ticket_created_at": "2025-03-14T17:16:51.711Z"}, "__v": 0, "created_at": "2024-12-16T20:16:10.571Z", "updated_at": "2025-03-14T17:16:51.727Z", "id": "67608a88e4a20e1238320570", "local_date_and_time": {"timezone": "GMT-10:00", "timezone_short": "GMT-10", "start_date": "3/16/2025", "start_time": "7:30 AM", "start_day_of_the_week": "Sunday", "end_date": "3/16/2025", "end_time": "7:40 AM", "end_day_of_the_week": "Sunday", "last_ticket_created_at": "Mar 14 at 7:16:51 AM"}}, {"event_id": "607fcb1a9196e149ac206742", "session_number": 34910, "app_id": "hanauma_bay", "location": {"id": "604bff314dde50e2de52c0e5", "name": "Hanauma Bay Orientation"}, "capacity": 15, "start_date_time": "2025-03-16T17:40:00.000Z", "end_date_time": "2025-03-16T18:00:00.000Z", "tags": [], "is_listed": true, "meta_data": {"tickets_issued": 17, "tickets_available": 0, "tickets_issued_and_invalid": 2, "tickets_issued_and_valid": 15, "last_ticket_created_at": "2025-03-14T17:16:02.576Z"}, "__v": 0, "created_at": "2024-12-16T20:16:10.572Z", "updated_at": "2025-03-14T17:16:02.587Z", "id": "67608a88e4a20e1238320571", "local_date_and_time": {"timezone": "GMT-10:00", "timezone_short": "GMT-10", "start_date": "3/16/2025", "start_time": "7:40 AM", "start_day_of_the_week": "Sunday", "end_date": "3/16/2025", "end_time": "8:00 AM", "end_day_of_the_week": "Sunday", "last_ticket_created_at": "Mar 14 at 7:16:02 AM"}}, {"event_id": "607fcb1a9196e149ac206742", "session_number": 34911, "app_id": "hanauma_bay", "location": {"id": "604bff314dde50e2de52c0e5", "name": "Hanauma Bay Orientation"}, "capacity": 35, "start_date_time": "2025-03-16T18:00:00.000Z", "end_date_time": "2025-03-16T18:10:00.000Z", "tags": [], "is_listed": true, "meta_data": {"tickets_issued": 61, "tickets_available": 0, "tickets_issued_and_invalid": 26, "tickets_issued_and_valid": 35, "last_ticket_created_at": "2025-03-14T17:32:38.821Z"}, "__v": 0, "created_at": "2024-12-16T20:16:10.572Z", "updated_at": "2025-03-14T18:29:48.260Z", "id": "67608a88e4a20e1238320572", "local_date_and_time": {"timezone": "GMT-10:00", "timezone_short": "GMT-10", "start_date": "3/16/2025", "start_time": "8:00 AM", "start_day_of_the_week": "Sunday", "end_date": "3/16/2025", "end_time": "8:10 AM", "end_day_of_the_week": "Sunday", "last_ticket_created_at": "Mar 14 at 7:32:38 AM"}}, {"event_id": "607fcb1a9196e149ac206742", "session_number": 34912, "app_id": "hanauma_bay", "location": {"id": "604bff314dde50e2de52c0e5", "name": "Hanauma Bay Orientation"}, "capacity": 35, "start_date_time": "2025-03-16T18:10:00.000Z", "end_date_time": "2025-03-16T18:20:00.000Z", "tags": [], "is_listed": true, "meta_data": {"tickets_issued": 50, "tickets_available": 0, "tickets_issued_and_invalid": 15, "tickets_issued_and_valid": 35, "last_ticket_created_at": "2025-03-14T17:18:18.106Z"}, "__v": 0, "created_at": "2024-12-16T20:16:10.572Z", "updated_at": "2025-03-14T17:18:18.126Z", "id": "67608a88e4a20e1238320573", "local_date_and_time": {"timezone": "GMT-10:00", "timezone_short": "GMT-10", "start_date": "3/16/2025", "start_time": "8:10 AM", "start_day_of_the_week": "Sunday", "end_date": "3/16/2025", "end_time": "8:20 AM", "end_day_of_the_week": "Sunday", "last_ticket_created_at": "Mar 14 at 7:18:18 AM"}}, {"event_id": "607fcb1a9196e149ac206742", "session_number": 34913, "app_id": "hanauma_bay", "location": {"id": "604bff314dde50e2de52c0e5", "name": "Hanauma Bay Orientation"}, "capacity": 35, "start_date_time": "2025-03-16T18:20:00.000Z", "end_date_time": "2025-03-16T18:30:00.000Z", "tags": [], "is_listed": true, "meta_data": {"tickets_issued": 46, "tickets_available": 0, "tickets_issued_and_invalid": 11, "tickets_issued_and_valid": 35, "last_ticket_created_at": "2025-03-14T17:19:44.622Z"}, "__v": 0, "created_at": "2024-12-16T20:16:10.572Z", "updated_at": "2025-03-14T17:19:44.645Z", "id": "67608a88e4a20e1238320574", "local_date_and_time": {"timezone": "GMT-10:00", "timezone_short": "GMT-10", "start_date": "3/16/2025", "start_time": "8:20 AM", "start_day_of_the_week": "Sunday", "end_date": "3/16/2025", "end_time": "8:30 AM", "end_day_of_the_week": "Sunday", "last_ticket_created_at": "Mar 14 at 7:19:44 AM"}}, {"event_id": "607fcb1a9196e149ac206742", "session_number": 34914, "app_id": "hanauma_bay", "location": {"id": "604bff314dde50e2de52c0e5", "name": "Hanauma Bay Orientation"}, "capacity": 35, "start_date_time": "2025-03-16T18:30:00.000Z", "end_date_time": "2025-03-16T18:40:00.000Z", "tags": [], "is_listed": true, "meta_data": {"tickets_issued": 48, "tickets_available": 0, "tickets_issued_and_invalid": 13, "tickets_issued_and_valid": 35, "last_ticket_created_at": "2025-03-14T17:18:30.540Z"}, "__v": 0, "created_at": "2024-12-16T20:16:10.572Z", "updated_at": "2025-03-14T17:18:30.549Z", "id": "67608a88e4a20e1238320575", "local_date_and_time": {"timezone": "GMT-10:00", "timezone_short": "GMT-10", "start_date": "3/16/2025", "start_time": "8:30 AM", "start_day_of_the_week": "Sunday", "end_date": "3/16/2025", "end_time": "8:40 AM", "end_day_of_the_week": "Sunday", "last_ticket_created_at": "Mar 14 at 7:18:30 AM"}}, {"event_id": "607fcb1a9196e149ac206742", "session_number": 34915, "app_id": "hanauma_bay", "location": {"id": "604bff314dde50e2de52c0e5", "name": "Hanauma Bay Orientation"}, "capacity": 35, "start_date_time": "2025-03-16T18:40:00.000Z", "end_date_time": "2025-03-16T19:00:00.000Z", "tags": [], "is_listed": true, "meta_data": {"tickets_issued": 35, "tickets_available": 0, "tickets_issued_and_invalid": 0, "tickets_issued_and_valid": 35, "last_ticket_created_at": "2025-03-14T17:04:55.288Z"}, "__v": 0, "created_at": "2024-12-16T20:16:10.572Z", "updated_at": "2025-03-14T17:04:55.296Z", "id": "67608a88e4a20e1238320576", "local_date_and_time": {"timezone": "GMT-10:00", "timezone_short": "GMT-10", "start_date": "3/16/2025", "start_time": "8:40 AM", "start_day_of_the_week": "Sunday", "end_date": "3/16/2025", "end_time": "9:00 AM", "end_day_of_the_week": "Sunday", "last_ticket_created_at": "Mar 14 at 7:04:55 AM"}}, {"event_id": "607fcb1a9196e149ac206742", "session_number": 34916, "app_id": "hanauma_bay", "location": {"id": "604bff314dde50e2de52c0e5", "name": "Hanauma Bay Orientation"}, "capacity": 35, "start_date_time": "2025-03-16T19:00:00.000Z", "end_date_time": "2025-03-16T19:10:00.000Z", "tags": [], "is_listed": true, "meta_data": {"tickets_issued": 35, "tickets_available": 0, "tickets_issued_and_invalid": 0, "tickets_issued_and_valid": 35, "last_ticket_created_at": "2025-03-14T17:01:38.390Z"}, "__v": 0, "created_at": "2024-12-16T20:16:10.572Z", "updated_at": "2025-03-14T17:01:38.411Z", "id": "67608a88e4a20e1238320577", "local_date_and_time": {"timezone": "GMT-10:00", "timezone_short": "GMT-10", "start_date": "3/16/2025", "start_time": "9:00 AM", "start_day_of_the_week": "Sunday", "end_date": "3/16/2025", "end_time": "9:10 AM", "end_day_of_the_week": "Sunday", "last_ticket_created_at": "Mar 14 at 7:01:38 AM"}}, {"event_id": "607fcb1a9196e149ac206742", "session_number": 34917, "app_id": "hanauma_bay", "location": {"id": "604bff314dde50e2de52c0e5", "name": "Hanauma Bay Orientation"}, "capacity": 35, "start_date_time": "2025-03-16T19:10:00.000Z", "end_date_time": "2025-03-16T19:20:00.000Z", "tags": [], "is_listed": true, "meta_data": {"tickets_issued": 37, "tickets_available": 0, "tickets_issued_and_invalid": 2, "tickets_issued_and_valid": 35, "last_ticket_created_at": "2025-03-14T17:16:21.048Z"}, "__v": 0, "created_at": "2024-12-16T20:16:10.572Z", "updated_at": "2025-03-14T17:16:21.060Z", "id": "67608a88e4a20e1238320578", "local_date_and_time": {"timezone": "GMT-10:00", "timezone_short": "GMT-10", "start_date": "3/16/2025", "start_time": "9:10 AM", "start_day_of_the_week": "Sunday", "end_date": "3/16/2025", "end_time": "9:20 AM", "end_day_of_the_week": "Sunday", "last_ticket_created_at": "Mar 14 at 7:16:21 AM"}}, {"event_id": "607fcb1a9196e149ac206742", "session_number": 34918, "app_id": "hanauma_bay", "location": {"id": "604bff314dde50e2de52c0e5", "name": "Hanauma Bay Orientation"}, "capacity": 35, "start_date_time": "2025-03-16T19:20:00.000Z", "end_date_time": "2025-03-16T19:30:00.000Z", "tags": [], "is_listed": true, "meta_data": {"tickets_issued": 36, "tickets_available": 0, "tickets_issued_and_invalid": 1, "tickets_issued_and_valid": 35, "last_ticket_created_at": "2025-03-14T17:05:55.809Z"}, "__v": 0, "created_at": "2024-12-16T20:16:10.572Z", "updated_at": "2025-03-14T17:05:55.817Z", "id": "67608a88e4a20e1238320579", "local_date_and_time": {"timezone": "GMT-10:00", "timezone_short": "GMT-10", "start_date": "3/16/2025", "start_time": "9:20 AM", "start_day_of_the_week": "Sunday", "end_date": "3/16/2025", "end_time": "9:30 AM", "end_day_of_the_week": "Sunday", "last_ticket_created_at": "Mar 14 at 7:05:55 AM"}}, {"event_id": "607fcb1a9196e149ac206742", "session_number": 34919, "app_id": "hanauma_bay", "location": {"id": "604bff314dde50e2de52c0e5", "name": "Hanauma Bay Orientation"}, "capacity": 35, "start_date_time": "2025-03-16T19:30:00.000Z", "end_date_time": "2025-03-16T19:40:00.000Z", "tags": [], "is_listed": true, "meta_data": {"tickets_issued": 35, "tickets_available": 0, "tickets_issued_and_invalid": 0, "tickets_issued_and_valid": 35, "last_ticket_created_at": "2025-03-14T17:01:36.521Z"}, "__v": 0, "created_at": "2024-12-16T20:16:10.572Z", "updated_at": "2025-03-14T17:01:36.534Z", "id": "67608a88e4a20e123832057a", "local_date_and_time": {"timezone": "GMT-10:00", "timezone_short": "GMT-10", "start_date": "3/16/2025", "start_time": "9:30 AM", "start_day_of_the_week": "Sunday", "end_date": "3/16/2025", "end_time": "9:40 AM", "end_day_of_the_week": "Sunday", "last_ticket_created_at": "Mar 14 at 7:01:36 AM"}}, {"event_id": "607fcb1a9196e149ac206742", "session_number": 34920, "app_id": "hanauma_bay", "location": {"id": "604bff314dde50e2de52c0e5", "name": "Hanauma Bay Orientation"}, "capacity": 35, "start_date_time": "2025-03-16T19:40:00.000Z", "end_date_time": "2025-03-16T20:00:00.000Z", "tags": [], "is_listed": true, "meta_data": {"tickets_issued": 39, "tickets_available": 0, "tickets_issued_and_invalid": 4, "tickets_issued_and_valid": 35, "last_ticket_created_at": "2025-03-14T17:03:10.918Z"}, "__v": 0, "created_at": "2024-12-16T20:16:10.572Z", "updated_at": "2025-03-14T17:03:10.931Z", "id": "67608a88e4a20e123832057b", "local_date_and_time": {"timezone": "GMT-10:00", "timezone_short": "GMT-10", "start_date": "3/16/2025", "start_time": "9:40 AM", "start_day_of_the_week": "Sunday", "end_date": "3/16/2025", "end_time": "10:00 AM", "end_day_of_the_week": "Sunday", "last_ticket_created_at": "Mar 14 at 7:03:10 AM"}}, {"event_id": "607fcb1a9196e149ac206742", "session_number": 34921, "app_id": "hanauma_bay", "location": {"id": "604bff314dde50e2de52c0e5", "name": "Hanauma Bay Orientation"}, "capacity": 35, "start_date_time": "2025-03-16T20:00:00.000Z", "end_date_time": "2025-03-16T20:10:00.000Z", "tags": [], "is_listed": true, "meta_data": {"tickets_issued": 39, "tickets_available": 0, "tickets_issued_and_invalid": 4, "tickets_issued_and_valid": 35, "last_ticket_created_at": "2025-03-14T17:02:32.440Z"}, "__v": 0, "created_at": "2024-12-16T20:16:10.572Z", "updated_at": "2025-03-14T17:02:32.455Z", "id": "67608a88e4a20e123832057c", "local_date_and_time": {"timezone": "GMT-10:00", "timezone_short": "GMT-10", "start_date": "3/16/2025", "start_time": "10:00 AM", "start_day_of_the_week": "Sunday", "end_date": "3/16/2025", "end_time": "10:10 AM", "end_day_of_the_week": "Sunday", "last_ticket_created_at": "Mar 14 at 7:02:32 AM"}}, {"event_id": "607fcb1a9196e149ac206742", "session_number": 34922, "app_id": "hanauma_bay", "location": {"id": "604bff314dde50e2de52c0e5", "name": "Hanauma Bay Orientation"}, "capacity": 35, "start_date_time": "2025-03-16T20:10:00.000Z", "end_date_time": "2025-03-16T20:20:00.000Z", "tags": [], "is_listed": true, "meta_data": {"tickets_issued": 35, "tickets_available": 0, "tickets_issued_and_invalid": 0, "tickets_issued_and_valid": 35, "last_ticket_created_at": "2025-03-14T17:03:31.502Z"}, "__v": 0, "created_at": "2024-12-16T20:16:10.573Z", "updated_at": "2025-03-14T17:03:31.517Z", "id": "67608a88e4a20e123832057d", "local_date_and_time": {"timezone": "GMT-10:00", "timezone_short": "GMT-10", "start_date": "3/16/2025", "start_time": "10:10 AM", "start_day_of_the_week": "Sunday", "end_date": "3/16/2025", "end_time": "10:20 AM", "end_day_of_the_week": "Sunday", "last_ticket_created_at": "Mar 14 at 7:03:31 AM"}}, {"event_id": "607fcb1a9196e149ac206742", "session_number": 34923, "app_id": "hanauma_bay", "location": {"id": "604bff314dde50e2de52c0e5", "name": "Hanauma Bay Orientation"}, "capacity": 35, "start_date_time": "2025-03-16T20:20:00.000Z", "end_date_time": "2025-03-16T20:30:00.000Z", "tags": [], "is_listed": true, "meta_data": {"tickets_issued": 44, "tickets_available": 0, "tickets_issued_and_invalid": 9, "tickets_issued_and_valid": 35, "last_ticket_created_at": "2025-03-14T17:14:24.039Z"}, "__v": 0, "created_at": "2024-12-16T20:16:10.573Z", "updated_at": "2025-03-14T17:14:24.054Z", "id": "67608a88e4a20e123832057e", "local_date_and_time": {"timezone": "GMT-10:00", "timezone_short": "GMT-10", "start_date": "3/16/2025", "start_time": "10:20 AM", "start_day_of_the_week": "Sunday", "end_date": "3/16/2025", "end_time": "10:30 AM", "end_day_of_the_week": "Sunday", "last_ticket_created_at": "Mar 14 at 7:14:24 AM"}}, {"event_id": "607fcb1a9196e149ac206742", "session_number": 34924, "app_id": "hanauma_bay", "location": {"id": "604bff314dde50e2de52c0e5", "name": "Hanauma Bay Orientation"}, "capacity": 35, "start_date_time": "2025-03-16T20:30:00.000Z", "end_date_time": "2025-03-16T20:40:00.000Z", "tags": [], "is_listed": true, "meta_data": {"tickets_issued": 44, "tickets_available": 0, "tickets_issued_and_invalid": 9, "tickets_issued_and_valid": 35, "last_ticket_created_at": "2025-03-14T17:23:17.903Z"}, "__v": 0, "created_at": "2024-12-16T20:16:10.573Z", "updated_at": "2025-03-14T17:23:17.924Z", "id": "67608a88e4a20e123832057f", "local_date_and_time": {"timezone": "GMT-10:00", "timezone_short": "GMT-10", "start_date": "3/16/2025", "start_time": "10:30 AM", "start_day_of_the_week": "Sunday", "end_date": "3/16/2025", "end_time": "10:40 AM", "end_day_of_the_week": "Sunday", "last_ticket_created_at": "Mar 14 at 7:23:17 AM"}}, {"event_id": "607fcb1a9196e149ac206742", "session_number": 34925, "app_id": "hanauma_bay", "location": {"id": "604bff314dde50e2de52c0e5", "name": "Hanauma Bay Orientation"}, "capacity": 35, "start_date_time": "2025-03-16T20:40:00.000Z", "end_date_time": "2025-03-16T21:00:00.000Z", "tags": [], "is_listed": true, "meta_data": {"tickets_issued": 44, "tickets_available": 0, "tickets_issued_and_invalid": 9, "tickets_issued_and_valid": 35, "last_ticket_created_at": "2025-03-14T17:18:11.252Z"}, "__v": 0, "created_at": "2024-12-16T20:16:10.573Z", "updated_at": "2025-03-14T17:18:11.264Z", "id": "67608a88e4a20e1238320580", "local_date_and_time": {"timezone": "GMT-10:00", "timezone_short": "GMT-10", "start_date": "3/16/2025", "start_time": "10:40 AM", "start_day_of_the_week": "Sunday", "end_date": "3/16/2025", "end_time": "11:00 AM", "end_day_of_the_week": "Sunday", "last_ticket_created_at": "Mar 14 at 7:18:11 AM"}}, {"event_id": "607fcb1a9196e149ac206742", "session_number": 34926, "app_id": "hanauma_bay", "location": {"id": "604bff314dde50e2de52c0e5", "name": "Hanauma Bay Orientation"}, "capacity": 35, "start_date_time": "2025-03-16T21:00:00.000Z", "end_date_time": "2025-03-16T21:10:00.000Z", "tags": [], "is_listed": true, "meta_data": {"tickets_issued": 37, "tickets_available": 0, "tickets_issued_and_invalid": 2, "tickets_issued_and_valid": 35, "last_ticket_created_at": "2025-03-14T17:12:43.528Z"}, "__v": 0, "created_at": "2024-12-16T20:16:10.573Z", "updated_at": "2025-03-14T17:12:43.542Z", "id": "67608a88e4a20e1238320581", "local_date_and_time": {"timezone": "GMT-10:00", "timezone_short": "GMT-10", "start_date": "3/16/2025", "start_time": "11:00 AM", "start_day_of_the_week": "Sunday", "end_date": "3/16/2025", "end_time": "11:10 AM", "end_day_of_the_week": "Sunday", "last_ticket_created_at": "Mar 14 at 7:12:43 AM"}}, {"event_id": "607fcb1a9196e149ac206742", "session_number": 34927, "app_id": "hanauma_bay", "location": {"id": "604bff314dde50e2de52c0e5", "name": "Hanauma Bay Orientation"}, "capacity": 35, "start_date_time": "2025-03-16T21:10:00.000Z", "end_date_time": "2025-03-16T21:20:00.000Z", "tags": [], "is_listed": true, "meta_data": {"tickets_issued": 40, "tickets_available": 0, "tickets_issued_and_invalid": 5, "tickets_issued_and_valid": 35, "last_ticket_created_at": "2025-03-14T17:04:26.300Z"}, "__v": 0, "created_at": "2024-12-16T20:16:10.573Z", "updated_at": "2025-03-14T17:04:26.308Z", "id": "67608a88e4a20e1238320582", "local_date_and_time": {"timezone": "GMT-10:00", "timezone_short": "GMT-10", "start_date": "3/16/2025", "start_time": "11:10 AM", "start_day_of_the_week": "Sunday", "end_date": "3/16/2025", "end_time": "11:20 AM", "end_day_of_the_week": "Sunday", "last_ticket_created_at": "Mar 14 at 7:04:26 AM"}}, {"event_id": "607fcb1a9196e149ac206742", "session_number": 34928, "app_id": "hanauma_bay", "location": {"id": "604bff314dde50e2de52c0e5", "name": "Hanauma Bay Orientation"}, "capacity": 35, "start_date_time": "2025-03-16T21:20:00.000Z", "end_date_time": "2025-03-16T21:30:00.000Z", "tags": [], "is_listed": true, "meta_data": {"tickets_issued": 35, "tickets_available": 0, "tickets_issued_and_invalid": 0, "tickets_issued_and_valid": 35, "last_ticket_created_at": "2025-03-14T17:04:42.648Z"}, "__v": 0, "created_at": "2024-12-16T20:16:10.573Z", "updated_at": "2025-03-14T17:04:42.659Z", "id": "67608a88e4a20e1238320583", "local_date_and_time": {"timezone": "GMT-10:00", "timezone_short": "GMT-10", "start_date": "3/16/2025", "start_time": "11:20 AM", "start_day_of_the_week": "Sunday", "end_date": "3/16/2025", "end_time": "11:30 AM", "end_day_of_the_week": "Sunday", "last_ticket_created_at": "Mar 14 at 7:04:42 AM"}}, {"event_id": "607fcb1a9196e149ac206742", "session_number": 34929, "app_id": "hanauma_bay", "location": {"id": "604bff314dde50e2de52c0e5", "name": "Hanauma Bay Orientation"}, "capacity": 35, "start_date_time": "2025-03-16T21:30:00.000Z", "end_date_time": "2025-03-16T21:40:00.000Z", "tags": [], "is_listed": true, "meta_data": {"tickets_issued": 36, "tickets_available": 0, "tickets_issued_and_invalid": 1, "tickets_issued_and_valid": 35, "last_ticket_created_at": "2025-03-14T17:05:17.264Z"}, "__v": 0, "created_at": "2024-12-16T20:16:10.573Z", "updated_at": "2025-03-14T17:05:17.273Z", "id": "67608a88e4a20e1238320584", "local_date_and_time": {"timezone": "GMT-10:00", "timezone_short": "GMT-10", "start_date": "3/16/2025", "start_time": "11:30 AM", "start_day_of_the_week": "Sunday", "end_date": "3/16/2025", "end_time": "11:40 AM", "end_day_of_the_week": "Sunday", "last_ticket_created_at": "Mar 14 at 7:05:17 AM"}}, {"event_id": "607fcb1a9196e149ac206742", "session_number": 34930, "app_id": "hanauma_bay", "location": {"id": "604bff314dde50e2de52c0e5", "name": "Hanauma Bay Orientation"}, "capacity": 35, "start_date_time": "2025-03-16T21:40:00.000Z", "end_date_time": "2025-03-16T22:00:00.000Z", "tags": [], "is_listed": true, "meta_data": {"tickets_issued": 39, "tickets_available": 0, "tickets_issued_and_invalid": 4, "tickets_issued_and_valid": 35, "last_ticket_created_at": "2025-03-14T17:13:01.231Z"}, "__v": 0, "created_at": "2024-12-16T20:16:10.573Z", "updated_at": "2025-03-14T17:13:01.249Z", "id": "67608a88e4a20e1238320585", "local_date_and_time": {"timezone": "GMT-10:00", "timezone_short": "GMT-10", "start_date": "3/16/2025", "start_time": "11:40 AM", "start_day_of_the_week": "Sunday", "end_date": "3/16/2025", "end_time": "12:00 PM", "end_day_of_the_week": "Sunday", "last_ticket_created_at": "Mar 14 at 7:13:01 AM"}}, {"event_id": "607fcb1a9196e149ac206742", "session_number": 34931, "app_id": "hanauma_bay", "location": {"id": "604bff314dde50e2de52c0e5", "name": "Hanauma Bay Orientation"}, "capacity": 35, "start_date_time": "2025-03-16T22:00:00.000Z", "end_date_time": "2025-03-16T22:10:00.000Z", "tags": [], "is_listed": true, "meta_data": {"tickets_issued": 37, "tickets_available": 0, "tickets_issued_and_invalid": 2, "tickets_issued_and_valid": 35, "last_ticket_created_at": "2025-03-14T17:06:52.531Z"}, "__v": 0, "created_at": "2024-12-16T20:16:10.573Z", "updated_at": "2025-03-14T17:06:52.545Z", "id": "67608a88e4a20e1238320586", "local_date_and_time": {"timezone": "GMT-10:00", "timezone_short": "GMT-10", "start_date": "3/16/2025", "start_time": "12:00 PM", "start_day_of_the_week": "Sunday", "end_date": "3/16/2025", "end_time": "12:10 PM", "end_day_of_the_week": "Sunday", "last_ticket_created_at": "Mar 14 at 7:06:52 AM"}}, {"event_id": "607fcb1a9196e149ac206742", "session_number": 34932, "app_id": "hanauma_bay", "location": {"id": "604bff314dde50e2de52c0e5", "name": "Hanauma Bay Orientation"}, "capacity": 35, "start_date_time": "2025-03-16T22:10:00.000Z", "end_date_time": "2025-03-16T22:20:00.000Z", "tags": [], "is_listed": true, "meta_data": {"tickets_issued": 42, "tickets_available": 0, "tickets_issued_and_invalid": 7, "tickets_issued_and_valid": 35, "last_ticket_created_at": "2025-03-14T17:09:37.820Z"}, "__v": 0, "created_at": "2024-12-16T20:16:10.573Z", "updated_at": "2025-03-14T17:09:37.834Z", "id": "67608a88e4a20e1238320587", "local_date_and_time": {"timezone": "GMT-10:00", "timezone_short": "GMT-10", "start_date": "3/16/2025", "start_time": "12:10 PM", "start_day_of_the_week": "Sunday", "end_date": "3/16/2025", "end_time": "12:20 PM", "end_day_of_the_week": "Sunday", "last_ticket_created_at": "Mar 14 at 7:09:37 AM"}}, {"event_id": "607fcb1a9196e149ac206742", "session_number": 34933, "app_id": "hanauma_bay", "location": {"id": "604bff314dde50e2de52c0e5", "name": "Hanauma Bay Orientation"}, "capacity": 35, "start_date_time": "2025-03-16T22:20:00.000Z", "end_date_time": "2025-03-16T22:30:00.000Z", "tags": [], "is_listed": true, "meta_data": {"tickets_issued": 39, "tickets_available": 0, "tickets_issued_and_invalid": 4, "tickets_issued_and_valid": 35, "last_ticket_created_at": "2025-03-14T17:07:59.160Z"}, "__v": 0, "created_at": "2024-12-16T20:16:10.573Z", "updated_at": "2025-03-14T17:07:59.170Z", "id": "67608a88e4a20e1238320588", "local_date_and_time": {"timezone": "GMT-10:00", "timezone_short": "GMT-10", "start_date": "3/16/2025", "start_time": "12:20 PM", "start_day_of_the_week": "Sunday", "end_date": "3/16/2025", "end_time": "12:30 PM", "end_day_of_the_week": "Sunday", "last_ticket_created_at": "Mar 14 at 7:07:59 AM"}}, {"event_id": "607fcb1a9196e149ac206742", "session_number": 34934, "app_id": "hanauma_bay", "location": {"id": "604bff314dde50e2de52c0e5", "name": "Hanauma Bay Orientation"}, "capacity": 35, "start_date_time": "2025-03-16T22:30:00.000Z", "end_date_time": "2025-03-16T22:40:00.000Z", "tags": [], "is_listed": true, "meta_data": {"tickets_issued": 45, "tickets_available": 0, "tickets_issued_and_invalid": 10, "tickets_issued_and_valid": 35, "last_ticket_created_at": "2025-03-14T17:20:05.124Z"}, "__v": 0, "created_at": "2024-12-16T20:16:10.574Z", "updated_at": "2025-03-14T17:20:05.145Z", "id": "67608a88e4a20e1238320589", "local_date_and_time": {"timezone": "GMT-10:00", "timezone_short": "GMT-10", "start_date": "3/16/2025", "start_time": "12:30 PM", "start_day_of_the_week": "Sunday", "end_date": "3/16/2025", "end_time": "12:40 PM", "end_day_of_the_week": "Sunday", "last_ticket_created_at": "Mar 14 at 7:20:05 AM"}}, {"event_id": "607fcb1a9196e149ac206742", "session_number": 34935, "app_id": "hanauma_bay", "location": {"id": "604bff314dde50e2de52c0e5", "name": "Hanauma Bay Orientation"}, "capacity": 35, "start_date_time": "2025-03-16T22:40:00.000Z", "end_date_time": "2025-03-16T23:00:00.000Z", "tags": [], "is_listed": true, "meta_data": {"tickets_issued": 39, "tickets_available": 0, "tickets_issued_and_invalid": 4, "tickets_issued_and_valid": 35, "last_ticket_created_at": "2025-03-14T17:15:00.470Z"}, "__v": 0, "created_at": "2024-12-16T20:16:10.574Z", "updated_at": "2025-03-14T17:15:00.486Z", "id": "67608a88e4a20e123832058a", "local_date_and_time": {"timezone": "GMT-10:00", "timezone_short": "GMT-10", "start_date": "3/16/2025", "start_time": "12:40 PM", "start_day_of_the_week": "Sunday", "end_date": "3/16/2025", "end_time": "1:00 PM", "end_day_of_the_week": "Sunday", "last_ticket_created_at": "Mar 14 at 7:15:00 AM"}}, {"event_id": "607fcb1a9196e149ac206742", "session_number": 34936, "app_id": "hanauma_bay", "location": {"id": "604bff314dde50e2de52c0e5", "name": "Hanauma Bay Orientation"}, "capacity": 35, "start_date_time": "2025-03-16T23:00:00.000Z", "end_date_time": "2025-03-16T23:10:00.000Z", "tags": [], "is_listed": true, "meta_data": {"tickets_issued": 39, "tickets_available": 0, "tickets_issued_and_invalid": 4, "tickets_issued_and_valid": 35, "last_ticket_created_at": "2025-03-14T17:07:18.513Z"}, "__v": 0, "created_at": "2024-12-16T20:16:10.574Z", "updated_at": "2025-03-14T17:07:18.522Z", "id": "67608a88e4a20e123832058b", "local_date_and_time": {"timezone": "GMT-10:00", "timezone_short": "GMT-10", "start_date": "3/16/2025", "start_time": "1:00 PM", "start_day_of_the_week": "Sunday", "end_date": "3/16/2025", "end_time": "1:10 PM", "end_day_of_the_week": "Sunday", "last_ticket_created_at": "Mar 14 at 7:07:18 AM"}}, {"event_id": "607fcb1a9196e149ac206742", "session_number": 34937, "app_id": "hanauma_bay", "location": {"id": "604bff314dde50e2de52c0e5", "name": "Hanauma Bay Orientation"}, "capacity": 35, "start_date_time": "2025-03-16T23:10:00.000Z", "end_date_time": "2025-03-16T23:20:00.000Z", "tags": [], "is_listed": true, "meta_data": {"tickets_issued": 42, "tickets_available": 0, "tickets_issued_and_invalid": 7, "tickets_issued_and_valid": 35, "last_ticket_created_at": "2025-03-14T17:07:00.181Z"}, "__v": 0, "created_at": "2024-12-16T20:16:10.574Z", "updated_at": "2025-03-14T17:07:00.191Z", "id": "67608a88e4a20e123832058c", "local_date_and_time": {"timezone": "GMT-10:00", "timezone_short": "GMT-10", "start_date": "3/16/2025", "start_time": "1:10 PM", "start_day_of_the_week": "Sunday", "end_date": "3/16/2025", "end_time": "1:20 PM", "end_day_of_the_week": "Sunday", "last_ticket_created_at": "Mar 14 at 7:07:00 AM"}}, {"event_id": "607fcb1a9196e149ac206742", "session_number": 34938, "app_id": "hanauma_bay", "location": {"id": "604bff314dde50e2de52c0e5", "name": "Hanauma Bay Orientation"}, "capacity": 30, "start_date_time": "2025-03-16T23:20:00.000Z", "end_date_time": "2025-03-16T23:30:00.000Z", "tags": [], "is_listed": true, "meta_data": {"tickets_issued": 36, "tickets_available": 0, "tickets_issued_and_invalid": 6, "tickets_issued_and_valid": 30, "last_ticket_created_at": "2025-03-14T17:17:45.210Z"}, "__v": 0, "created_at": "2024-12-16T20:16:10.574Z", "updated_at": "2025-03-14T17:17:45.238Z", "id": "67608a88e4a20e123832058d", "local_date_and_time": {"timezone": "GMT-10:00", "timezone_short": "GMT-10", "start_date": "3/16/2025", "start_time": "1:20 PM", "start_day_of_the_week": "Sunday", "end_date": "3/16/2025", "end_time": "1:30 PM", "end_day_of_the_week": "Sunday", "last_ticket_created_at": "Mar 14 at 7:17:45 AM"}}]}}