{"meta": {"page": {"size": 50, "number": 1}, "count": 33}, "data": {"event_sessions": [{"event_id": "607fcb1a9196e149ac206742", "session_number": 35698, "app_id": "hanauma_bay", "location": {"id": "604bff314dde50e2de52c0e5", "name": "Hanauma Bay Orientation"}, "capacity": 15, "start_date_time": "2025-04-19T17:00:00.000Z", "end_date_time": "2025-04-19T17:10:00.000Z", "tags": [], "is_listed": true, "meta_data": {"tickets_issued": 1355, "tickets_available": 0, "tickets_issued_and_invalid": 1340, "tickets_issued_and_valid": 15, "last_ticket_created_at": "2025-04-17T20:25:25.883Z"}, "__v": 0, "created_at": "2024-12-16T20:16:10.653Z", "updated_at": "2025-04-17T20:25:26.123Z", "id": "67608a88e4a20e1238320885", "local_date_and_time": {"timezone": "GMT-10:00", "timezone_short": "GMT-10", "start_date": "4/19/2025", "start_time": "7:00 AM", "start_day_of_the_week": "Saturday", "end_date": "4/19/2025", "end_time": "7:10 AM", "end_day_of_the_week": "Saturday", "last_ticket_created_at": "Apr 17 at 10:25:25 AM"}}, {"event_id": "607fcb1a9196e149ac206742", "session_number": 35699, "app_id": "hanauma_bay", "location": {"id": "604bff314dde50e2de52c0e5", "name": "Hanauma Bay Orientation"}, "capacity": 15, "start_date_time": "2025-04-19T17:10:00.000Z", "end_date_time": "2025-04-19T17:20:00.000Z", "tags": [], "is_listed": true, "meta_data": {"tickets_issued": 835, "tickets_available": 0, "tickets_issued_and_invalid": 820, "tickets_issued_and_valid": 15, "last_ticket_created_at": "2025-04-17T20:20:14.125Z"}, "__v": 0, "created_at": "2024-12-16T20:16:10.653Z", "updated_at": "2025-04-17T20:20:14.337Z", "id": "67608a88e4a20e1238320886", "local_date_and_time": {"timezone": "GMT-10:00", "timezone_short": "GMT-10", "start_date": "4/19/2025", "start_time": "7:10 AM", "start_day_of_the_week": "Saturday", "end_date": "4/19/2025", "end_time": "7:20 AM", "end_day_of_the_week": "Saturday", "last_ticket_created_at": "Apr 17 at 10:20:14 AM"}}, {"event_id": "607fcb1a9196e149ac206742", "session_number": 35700, "app_id": "hanauma_bay", "location": {"id": "604bff314dde50e2de52c0e5", "name": "Hanauma Bay Orientation"}, "capacity": 15, "start_date_time": "2025-04-19T17:20:00.000Z", "end_date_time": "2025-04-19T17:30:00.000Z", "tags": [], "is_listed": true, "meta_data": {"tickets_issued": 2357, "tickets_available": 0, "tickets_issued_and_invalid": 2342, "tickets_issued_and_valid": 15, "last_ticket_created_at": "2025-04-17T19:55:42.617Z"}, "__v": 0, "created_at": "2024-12-16T20:16:10.653Z", "updated_at": "2025-04-17T19:55:42.859Z", "id": "67608a88e4a20e1238320887", "local_date_and_time": {"timezone": "GMT-10:00", "timezone_short": "GMT-10", "start_date": "4/19/2025", "start_time": "7:20 AM", "start_day_of_the_week": "Saturday", "end_date": "4/19/2025", "end_time": "7:30 AM", "end_day_of_the_week": "Saturday", "last_ticket_created_at": "Apr 17 at 9:55:42 AM"}}, {"event_id": "607fcb1a9196e149ac206742", "session_number": 35701, "app_id": "hanauma_bay", "location": {"id": "604bff314dde50e2de52c0e5", "name": "Hanauma Bay Orientation"}, "capacity": 15, "start_date_time": "2025-04-19T17:30:00.000Z", "end_date_time": "2025-04-19T17:40:00.000Z", "tags": [], "is_listed": true, "meta_data": {"tickets_issued": 2383, "tickets_available": 0, "tickets_issued_and_invalid": 2368, "tickets_issued_and_valid": 15, "last_ticket_created_at": "2025-04-17T20:42:34.858Z"}, "__v": 0, "created_at": "2024-12-16T20:16:10.653Z", "updated_at": "2025-04-17T20:42:35.311Z", "id": "67608a88e4a20e1238320888", "local_date_and_time": {"timezone": "GMT-10:00", "timezone_short": "GMT-10", "start_date": "4/19/2025", "start_time": "7:30 AM", "start_day_of_the_week": "Saturday", "end_date": "4/19/2025", "end_time": "7:40 AM", "end_day_of_the_week": "Saturday", "last_ticket_created_at": "Apr 17 at 10:42:34 AM"}}, {"event_id": "607fcb1a9196e149ac206742", "session_number": 35702, "app_id": "hanauma_bay", "location": {"id": "604bff314dde50e2de52c0e5", "name": "Hanauma Bay Orientation"}, "capacity": 15, "start_date_time": "2025-04-19T17:40:00.000Z", "end_date_time": "2025-04-19T18:00:00.000Z", "tags": [], "is_listed": true, "meta_data": {"tickets_issued": 1063, "tickets_available": 0, "tickets_issued_and_invalid": 1048, "tickets_issued_and_valid": 15, "last_ticket_created_at": "2025-04-17T21:01:57.513Z"}, "__v": 0, "created_at": "2024-12-16T20:16:10.653Z", "updated_at": "2025-04-17T21:01:57.738Z", "id": "67608a88e4a20e1238320889", "local_date_and_time": {"timezone": "GMT-10:00", "timezone_short": "GMT-10", "start_date": "4/19/2025", "start_time": "7:40 AM", "start_day_of_the_week": "Saturday", "end_date": "4/19/2025", "end_time": "8:00 AM", "end_day_of_the_week": "Saturday", "last_ticket_created_at": "Apr 17 at 11:01:57 AM"}}, {"event_id": "607fcb1a9196e149ac206742", "session_number": 35703, "app_id": "hanauma_bay", "location": {"id": "604bff314dde50e2de52c0e5", "name": "Hanauma Bay Orientation"}, "capacity": 35, "start_date_time": "2025-04-19T18:00:00.000Z", "end_date_time": "2025-04-19T18:10:00.000Z", "tags": [], "is_listed": true, "meta_data": {"tickets_issued": 3720, "tickets_available": 0, "tickets_issued_and_invalid": 3685, "tickets_issued_and_valid": 35, "last_ticket_created_at": "2025-04-17T20:44:20.724Z"}, "__v": 0, "created_at": "2024-12-16T20:16:10.653Z", "updated_at": "2025-04-17T20:44:21.542Z", "id": "67608a88e4a20e123832088a", "local_date_and_time": {"timezone": "GMT-10:00", "timezone_short": "GMT-10", "start_date": "4/19/2025", "start_time": "8:00 AM", "start_day_of_the_week": "Saturday", "end_date": "4/19/2025", "end_time": "8:10 AM", "end_day_of_the_week": "Saturday", "last_ticket_created_at": "Apr 17 at 10:44:20 AM"}}, {"event_id": "607fcb1a9196e149ac206742", "session_number": 35704, "app_id": "hanauma_bay", "location": {"id": "604bff314dde50e2de52c0e5", "name": "Hanauma Bay Orientation"}, "capacity": 35, "start_date_time": "2025-04-19T18:10:00.000Z", "end_date_time": "2025-04-19T18:20:00.000Z", "tags": [], "is_listed": true, "meta_data": {"tickets_issued": 4388, "tickets_available": 0, "tickets_issued_and_invalid": 4353, "tickets_issued_and_valid": 35, "last_ticket_created_at": "2025-04-17T19:38:35.541Z"}, "__v": 0, "created_at": "2024-12-16T20:16:10.653Z", "updated_at": "2025-04-17T19:38:36.045Z", "id": "67608a88e4a20e123832088b", "local_date_and_time": {"timezone": "GMT-10:00", "timezone_short": "GMT-10", "start_date": "4/19/2025", "start_time": "8:10 AM", "start_day_of_the_week": "Saturday", "end_date": "4/19/2025", "end_time": "8:20 AM", "end_day_of_the_week": "Saturday", "last_ticket_created_at": "Apr 17 at 9:38:35 AM"}}, {"event_id": "607fcb1a9196e149ac206742", "session_number": 35705, "app_id": "hanauma_bay", "location": {"id": "604bff314dde50e2de52c0e5", "name": "Hanauma Bay Orientation"}, "capacity": 35, "start_date_time": "2025-04-19T18:20:00.000Z", "end_date_time": "2025-04-19T18:30:00.000Z", "tags": [], "is_listed": true, "meta_data": {"tickets_issued": 2743, "tickets_available": 0, "tickets_issued_and_invalid": 2708, "tickets_issued_and_valid": 35, "last_ticket_created_at": "2025-04-17T20:17:53.231Z"}, "__v": 0, "created_at": "2024-12-16T20:16:10.653Z", "updated_at": "2025-04-17T20:17:53.713Z", "id": "67608a88e4a20e123832088c", "local_date_and_time": {"timezone": "GMT-10:00", "timezone_short": "GMT-10", "start_date": "4/19/2025", "start_time": "8:20 AM", "start_day_of_the_week": "Saturday", "end_date": "4/19/2025", "end_time": "8:30 AM", "end_day_of_the_week": "Saturday", "last_ticket_created_at": "Apr 17 at 10:17:53 AM"}}, {"event_id": "607fcb1a9196e149ac206742", "session_number": 35706, "app_id": "hanauma_bay", "location": {"id": "604bff314dde50e2de52c0e5", "name": "Hanauma Bay Orientation"}, "capacity": 35, "start_date_time": "2025-04-19T18:30:00.000Z", "end_date_time": "2025-04-19T18:40:00.000Z", "tags": [], "is_listed": true, "meta_data": {"tickets_issued": 6360, "tickets_available": 0, "tickets_issued_and_invalid": 6325, "tickets_issued_and_valid": 35, "last_ticket_created_at": "2025-04-17T20:34:18.472Z"}, "__v": 0, "created_at": "2024-12-16T20:16:10.653Z", "updated_at": "2025-04-17T20:34:19.226Z", "id": "67608a88e4a20e123832088d", "local_date_and_time": {"timezone": "GMT-10:00", "timezone_short": "GMT-10", "start_date": "4/19/2025", "start_time": "8:30 AM", "start_day_of_the_week": "Saturday", "end_date": "4/19/2025", "end_time": "8:40 AM", "end_day_of_the_week": "Saturday", "last_ticket_created_at": "Apr 17 at 10:34:18 AM"}}, {"event_id": "607fcb1a9196e149ac206742", "session_number": 35707, "app_id": "hanauma_bay", "location": {"id": "604bff314dde50e2de52c0e5", "name": "Hanauma Bay Orientation"}, "capacity": 35, "start_date_time": "2025-04-19T18:40:00.000Z", "end_date_time": "2025-04-19T19:00:00.000Z", "tags": [], "is_listed": true, "meta_data": {"tickets_issued": 3775, "tickets_available": 0, "tickets_issued_and_invalid": 3740, "tickets_issued_and_valid": 35, "last_ticket_created_at": "2025-04-17T20:20:34.067Z"}, "__v": 0, "created_at": "2024-12-16T20:16:10.653Z", "updated_at": "2025-04-17T20:20:34.725Z", "id": "67608a88e4a20e123832088e", "local_date_and_time": {"timezone": "GMT-10:00", "timezone_short": "GMT-10", "start_date": "4/19/2025", "start_time": "8:40 AM", "start_day_of_the_week": "Saturday", "end_date": "4/19/2025", "end_time": "9:00 AM", "end_day_of_the_week": "Saturday", "last_ticket_created_at": "Apr 17 at 10:20:34 AM"}}, {"event_id": "607fcb1a9196e149ac206742", "session_number": 35708, "app_id": "hanauma_bay", "location": {"id": "604bff314dde50e2de52c0e5", "name": "Hanauma Bay Orientation"}, "capacity": 35, "start_date_time": "2025-04-19T19:00:00.000Z", "end_date_time": "2025-04-19T19:10:00.000Z", "tags": [], "is_listed": true, "meta_data": {"tickets_issued": 6145, "tickets_available": 0, "tickets_issued_and_invalid": 6110, "tickets_issued_and_valid": 35, "last_ticket_created_at": "2025-04-17T20:18:31.690Z"}, "__v": 0, "created_at": "2024-12-16T20:16:10.653Z", "updated_at": "2025-04-17T20:18:32.960Z", "id": "67608a88e4a20e123832088f", "local_date_and_time": {"timezone": "GMT-10:00", "timezone_short": "GMT-10", "start_date": "4/19/2025", "start_time": "9:00 AM", "start_day_of_the_week": "Saturday", "end_date": "4/19/2025", "end_time": "9:10 AM", "end_day_of_the_week": "Saturday", "last_ticket_created_at": "Apr 17 at 10:18:31 AM"}}, {"event_id": "607fcb1a9196e149ac206742", "session_number": 35709, "app_id": "hanauma_bay", "location": {"id": "604bff314dde50e2de52c0e5", "name": "Hanauma Bay Orientation"}, "capacity": 35, "start_date_time": "2025-04-19T19:10:00.000Z", "end_date_time": "2025-04-19T19:20:00.000Z", "tags": [], "is_listed": true, "meta_data": {"tickets_issued": 4672, "tickets_available": 0, "tickets_issued_and_invalid": 4637, "tickets_issued_and_valid": 35, "last_ticket_created_at": "2025-04-17T20:38:13.996Z"}, "__v": 0, "created_at": "2024-12-16T20:16:10.654Z", "updated_at": "2025-04-17T20:38:14.772Z", "id": "67608a88e4a20e1238320890", "local_date_and_time": {"timezone": "GMT-10:00", "timezone_short": "GMT-10", "start_date": "4/19/2025", "start_time": "9:10 AM", "start_day_of_the_week": "Saturday", "end_date": "4/19/2025", "end_time": "9:20 AM", "end_day_of_the_week": "Saturday", "last_ticket_created_at": "Apr 17 at 10:38:13 AM"}}, {"event_id": "607fcb1a9196e149ac206742", "session_number": 35710, "app_id": "hanauma_bay", "location": {"id": "604bff314dde50e2de52c0e5", "name": "Hanauma Bay Orientation"}, "capacity": 35, "start_date_time": "2025-04-19T19:20:00.000Z", "end_date_time": "2025-04-19T19:30:00.000Z", "tags": [], "is_listed": true, "meta_data": {"tickets_issued": 4556, "tickets_available": 0, "tickets_issued_and_invalid": 4521, "tickets_issued_and_valid": 35, "last_ticket_created_at": "2025-04-17T20:30:08.688Z"}, "__v": 0, "created_at": "2024-12-16T20:16:10.654Z", "updated_at": "2025-04-17T20:30:09.359Z", "id": "67608a88e4a20e1238320891", "local_date_and_time": {"timezone": "GMT-10:00", "timezone_short": "GMT-10", "start_date": "4/19/2025", "start_time": "9:20 AM", "start_day_of_the_week": "Saturday", "end_date": "4/19/2025", "end_time": "9:30 AM", "end_day_of_the_week": "Saturday", "last_ticket_created_at": "Apr 17 at 10:30:08 AM"}}, {"event_id": "607fcb1a9196e149ac206742", "session_number": 35711, "app_id": "hanauma_bay", "location": {"id": "604bff314dde50e2de52c0e5", "name": "Hanauma Bay Orientation"}, "capacity": 35, "start_date_time": "2025-04-19T19:30:00.000Z", "end_date_time": "2025-04-19T19:40:00.000Z", "tags": [], "is_listed": true, "meta_data": {"tickets_issued": 3485, "tickets_available": 0, "tickets_issued_and_invalid": 3450, "tickets_issued_and_valid": 35, "last_ticket_created_at": "2025-04-17T20:17:35.853Z"}, "__v": 0, "created_at": "2024-12-16T20:16:10.654Z", "updated_at": "2025-04-17T20:17:36.161Z", "id": "67608a88e4a20e1238320892", "local_date_and_time": {"timezone": "GMT-10:00", "timezone_short": "GMT-10", "start_date": "4/19/2025", "start_time": "9:30 AM", "start_day_of_the_week": "Saturday", "end_date": "4/19/2025", "end_time": "9:40 AM", "end_day_of_the_week": "Saturday", "last_ticket_created_at": "Apr 17 at 10:17:35 AM"}}, {"event_id": "607fcb1a9196e149ac206742", "session_number": 35712, "app_id": "hanauma_bay", "location": {"id": "604bff314dde50e2de52c0e5", "name": "Hanauma Bay Orientation"}, "capacity": 35, "start_date_time": "2025-04-19T19:40:00.000Z", "end_date_time": "2025-04-19T20:00:00.000Z", "tags": [], "is_listed": true, "meta_data": {"tickets_issued": 5710, "tickets_available": 0, "tickets_issued_and_invalid": 5675, "tickets_issued_and_valid": 35, "last_ticket_created_at": "2025-04-17T20:30:32.590Z"}, "__v": 0, "created_at": "2024-12-16T20:16:10.654Z", "updated_at": "2025-04-17T20:30:33.367Z", "id": "67608a88e4a20e1238320893", "local_date_and_time": {"timezone": "GMT-10:00", "timezone_short": "GMT-10", "start_date": "4/19/2025", "start_time": "9:40 AM", "start_day_of_the_week": "Saturday", "end_date": "4/19/2025", "end_time": "10:00 AM", "end_day_of_the_week": "Saturday", "last_ticket_created_at": "Apr 17 at 10:30:32 AM"}}, {"event_id": "607fcb1a9196e149ac206742", "session_number": 35713, "app_id": "hanauma_bay", "location": {"id": "604bff314dde50e2de52c0e5", "name": "Hanauma Bay Orientation"}, "capacity": 35, "start_date_time": "2025-04-19T20:00:00.000Z", "end_date_time": "2025-04-19T20:10:00.000Z", "tags": [], "is_listed": true, "meta_data": {"tickets_issued": 6168, "tickets_available": 0, "tickets_issued_and_invalid": 6133, "tickets_issued_and_valid": 35, "last_ticket_created_at": "2025-04-17T20:17:46.192Z"}, "__v": 0, "created_at": "2024-12-16T20:16:10.654Z", "updated_at": "2025-04-17T20:17:46.973Z", "id": "67608a88e4a20e1238320894", "local_date_and_time": {"timezone": "GMT-10:00", "timezone_short": "GMT-10", "start_date": "4/19/2025", "start_time": "10:00 AM", "start_day_of_the_week": "Saturday", "end_date": "4/19/2025", "end_time": "10:10 AM", "end_day_of_the_week": "Saturday", "last_ticket_created_at": "Apr 17 at 10:17:46 AM"}}, {"event_id": "607fcb1a9196e149ac206742", "session_number": 35714, "app_id": "hanauma_bay", "location": {"id": "604bff314dde50e2de52c0e5", "name": "Hanauma Bay Orientation"}, "capacity": 35, "start_date_time": "2025-04-19T20:10:00.000Z", "end_date_time": "2025-04-19T20:20:00.000Z", "tags": [], "is_listed": true, "meta_data": {"tickets_issued": 6849, "tickets_available": 0, "tickets_issued_and_invalid": 6814, "tickets_issued_and_valid": 35, "last_ticket_created_at": "2025-04-17T20:29:52.163Z"}, "__v": 0, "created_at": "2024-12-16T20:16:10.654Z", "updated_at": "2025-04-17T20:29:52.897Z", "id": "67608a88e4a20e1238320895", "local_date_and_time": {"timezone": "GMT-10:00", "timezone_short": "GMT-10", "start_date": "4/19/2025", "start_time": "10:10 AM", "start_day_of_the_week": "Saturday", "end_date": "4/19/2025", "end_time": "10:20 AM", "end_day_of_the_week": "Saturday", "last_ticket_created_at": "Apr 17 at 10:29:52 AM"}}, {"event_id": "607fcb1a9196e149ac206742", "session_number": 35715, "app_id": "hanauma_bay", "location": {"id": "604bff314dde50e2de52c0e5", "name": "Hanauma Bay Orientation"}, "capacity": 35, "start_date_time": "2025-04-19T20:20:00.000Z", "end_date_time": "2025-04-19T20:30:00.000Z", "tags": [], "is_listed": true, "meta_data": {"tickets_issued": 6437, "tickets_available": 0, "tickets_issued_and_invalid": 6402, "tickets_issued_and_valid": 35, "last_ticket_created_at": "2025-04-17T20:18:02.817Z"}, "__v": 0, "created_at": "2024-12-16T20:16:10.654Z", "updated_at": "2025-04-17T20:18:04.232Z", "id": "67608a88e4a20e1238320896", "local_date_and_time": {"timezone": "GMT-10:00", "timezone_short": "GMT-10", "start_date": "4/19/2025", "start_time": "10:20 AM", "start_day_of_the_week": "Saturday", "end_date": "4/19/2025", "end_time": "10:30 AM", "end_day_of_the_week": "Saturday", "last_ticket_created_at": "Apr 17 at 10:18:02 AM"}}, {"event_id": "607fcb1a9196e149ac206742", "session_number": 35716, "app_id": "hanauma_bay", "location": {"id": "604bff314dde50e2de52c0e5", "name": "Hanauma Bay Orientation"}, "capacity": 35, "start_date_time": "2025-04-19T20:30:00.000Z", "end_date_time": "2025-04-19T20:40:00.000Z", "tags": [], "is_listed": true, "meta_data": {"tickets_issued": 5031, "tickets_available": 0, "tickets_issued_and_invalid": 4996, "tickets_issued_and_valid": 35, "last_ticket_created_at": "2025-04-17T20:31:24.615Z"}, "__v": 0, "created_at": "2024-12-16T20:16:10.654Z", "updated_at": "2025-04-17T20:31:25.454Z", "id": "67608a88e4a20e1238320897", "local_date_and_time": {"timezone": "GMT-10:00", "timezone_short": "GMT-10", "start_date": "4/19/2025", "start_time": "10:30 AM", "start_day_of_the_week": "Saturday", "end_date": "4/19/2025", "end_time": "10:40 AM", "end_day_of_the_week": "Saturday", "last_ticket_created_at": "Apr 17 at 10:31:24 AM"}}, {"event_id": "607fcb1a9196e149ac206742", "session_number": 35717, "app_id": "hanauma_bay", "location": {"id": "604bff314dde50e2de52c0e5", "name": "Hanauma Bay Orientation"}, "capacity": 35, "start_date_time": "2025-04-19T20:40:00.000Z", "end_date_time": "2025-04-19T21:00:00.000Z", "tags": [], "is_listed": true, "meta_data": {"tickets_issued": 4742, "tickets_available": 0, "tickets_issued_and_invalid": 4707, "tickets_issued_and_valid": 35, "last_ticket_created_at": "2025-04-17T20:33:29.896Z"}, "__v": 0, "created_at": "2024-12-16T20:16:10.654Z", "updated_at": "2025-04-17T20:33:30.785Z", "id": "67608a88e4a20e1238320898", "local_date_and_time": {"timezone": "GMT-10:00", "timezone_short": "GMT-10", "start_date": "4/19/2025", "start_time": "10:40 AM", "start_day_of_the_week": "Saturday", "end_date": "4/19/2025", "end_time": "11:00 AM", "end_day_of_the_week": "Saturday", "last_ticket_created_at": "Apr 17 at 10:33:29 AM"}}, {"event_id": "607fcb1a9196e149ac206742", "session_number": 35718, "app_id": "hanauma_bay", "location": {"id": "604bff314dde50e2de52c0e5", "name": "Hanauma Bay Orientation"}, "capacity": 35, "start_date_time": "2025-04-19T21:00:00.000Z", "end_date_time": "2025-04-19T21:10:00.000Z", "tags": [], "is_listed": true, "meta_data": {"tickets_issued": 3071, "tickets_available": 0, "tickets_issued_and_invalid": 3036, "tickets_issued_and_valid": 35, "last_ticket_created_at": "2025-04-17T20:40:36.246Z"}, "__v": 0, "created_at": "2024-12-16T20:16:10.654Z", "updated_at": "2025-04-17T20:40:36.796Z", "id": "67608a88e4a20e1238320899", "local_date_and_time": {"timezone": "GMT-10:00", "timezone_short": "GMT-10", "start_date": "4/19/2025", "start_time": "11:00 AM", "start_day_of_the_week": "Saturday", "end_date": "4/19/2025", "end_time": "11:10 AM", "end_day_of_the_week": "Saturday", "last_ticket_created_at": "Apr 17 at 10:40:36 AM"}}, {"event_id": "607fcb1a9196e149ac206742", "session_number": 35719, "app_id": "hanauma_bay", "location": {"id": "604bff314dde50e2de52c0e5", "name": "Hanauma Bay Orientation"}, "capacity": 35, "start_date_time": "2025-04-19T21:10:00.000Z", "end_date_time": "2025-04-19T21:20:00.000Z", "tags": [], "is_listed": true, "meta_data": {"tickets_issued": 3995, "tickets_available": 0, "tickets_issued_and_invalid": 3960, "tickets_issued_and_valid": 35, "last_ticket_created_at": "2025-04-17T20:58:58.695Z"}, "__v": 0, "created_at": "2024-12-16T20:16:10.654Z", "updated_at": "2025-04-17T20:58:59.275Z", "id": "67608a88e4a20e123832089a", "local_date_and_time": {"timezone": "GMT-10:00", "timezone_short": "GMT-10", "start_date": "4/19/2025", "start_time": "11:10 AM", "start_day_of_the_week": "Saturday", "end_date": "4/19/2025", "end_time": "11:20 AM", "end_day_of_the_week": "Saturday", "last_ticket_created_at": "Apr 17 at 10:58:58 AM"}}, {"event_id": "607fcb1a9196e149ac206742", "session_number": 35720, "app_id": "hanauma_bay", "location": {"id": "604bff314dde50e2de52c0e5", "name": "Hanauma Bay Orientation"}, "capacity": 35, "start_date_time": "2025-04-19T21:20:00.000Z", "end_date_time": "2025-04-19T21:30:00.000Z", "tags": [], "is_listed": true, "meta_data": {"tickets_issued": 4038, "tickets_available": 0, "tickets_issued_and_invalid": 4003, "tickets_issued_and_valid": 35, "last_ticket_created_at": "2025-04-17T20:34:12.855Z"}, "__v": 0, "created_at": "2024-12-16T20:16:10.654Z", "updated_at": "2025-04-17T20:34:13.675Z", "id": "67608a88e4a20e123832089b", "local_date_and_time": {"timezone": "GMT-10:00", "timezone_short": "GMT-10", "start_date": "4/19/2025", "start_time": "11:20 AM", "start_day_of_the_week": "Saturday", "end_date": "4/19/2025", "end_time": "11:30 AM", "end_day_of_the_week": "Saturday", "last_ticket_created_at": "Apr 17 at 10:34:12 AM"}}, {"event_id": "607fcb1a9196e149ac206742", "session_number": 35721, "app_id": "hanauma_bay", "location": {"id": "604bff314dde50e2de52c0e5", "name": "Hanauma Bay Orientation"}, "capacity": 35, "start_date_time": "2025-04-19T21:30:00.000Z", "end_date_time": "2025-04-19T21:40:00.000Z", "tags": [], "is_listed": true, "meta_data": {"tickets_issued": 2213, "tickets_available": 0, "tickets_issued_and_invalid": 2178, "tickets_issued_and_valid": 35, "last_ticket_created_at": "2025-04-18T00:49:05.610Z"}, "__v": 0, "created_at": "2024-12-16T20:16:10.654Z", "updated_at": "2025-04-18T00:49:06.036Z", "id": "67608a88e4a20e123832089c", "local_date_and_time": {"timezone": "GMT-10:00", "timezone_short": "GMT-10", "start_date": "4/19/2025", "start_time": "11:30 AM", "start_day_of_the_week": "Saturday", "end_date": "4/19/2025", "end_time": "11:40 AM", "end_day_of_the_week": "Saturday", "last_ticket_created_at": "Apr 17 at 2:49:05 PM"}}, {"event_id": "607fcb1a9196e149ac206742", "session_number": 35722, "app_id": "hanauma_bay", "location": {"id": "604bff314dde50e2de52c0e5", "name": "Hanauma Bay Orientation"}, "capacity": 35, "start_date_time": "2025-04-19T21:40:00.000Z", "end_date_time": "2025-04-19T22:00:00.000Z", "tags": [], "is_listed": true, "meta_data": {"tickets_issued": 2527, "tickets_available": 0, "tickets_issued_and_invalid": 2492, "tickets_issued_and_valid": 35, "last_ticket_created_at": "2025-04-17T20:27:45.453Z"}, "__v": 0, "created_at": "2024-12-16T20:16:10.654Z", "updated_at": "2025-04-17T20:27:45.745Z", "id": "67608a88e4a20e123832089d", "local_date_and_time": {"timezone": "GMT-10:00", "timezone_short": "GMT-10", "start_date": "4/19/2025", "start_time": "11:40 AM", "start_day_of_the_week": "Saturday", "end_date": "4/19/2025", "end_time": "12:00 PM", "end_day_of_the_week": "Saturday", "last_ticket_created_at": "Apr 17 at 10:27:45 AM"}}, {"event_id": "607fcb1a9196e149ac206742", "session_number": 35723, "app_id": "hanauma_bay", "location": {"id": "604bff314dde50e2de52c0e5", "name": "Hanauma Bay Orientation"}, "capacity": 35, "start_date_time": "2025-04-19T22:00:00.000Z", "end_date_time": "2025-04-19T22:10:00.000Z", "tags": [], "is_listed": true, "meta_data": {"tickets_issued": 2732, "tickets_available": 0, "tickets_issued_and_invalid": 2697, "tickets_issued_and_valid": 35, "last_ticket_created_at": "2025-04-17T20:33:39.618Z"}, "__v": 0, "created_at": "2024-12-16T20:16:10.654Z", "updated_at": "2025-04-17T20:33:40.161Z", "id": "67608a88e4a20e123832089e", "local_date_and_time": {"timezone": "GMT-10:00", "timezone_short": "GMT-10", "start_date": "4/19/2025", "start_time": "12:00 PM", "start_day_of_the_week": "Saturday", "end_date": "4/19/2025", "end_time": "12:10 PM", "end_day_of_the_week": "Saturday", "last_ticket_created_at": "Apr 17 at 10:33:39 AM"}}, {"event_id": "607fcb1a9196e149ac206742", "session_number": 35724, "app_id": "hanauma_bay", "location": {"id": "604bff314dde50e2de52c0e5", "name": "Hanauma Bay Orientation"}, "capacity": 35, "start_date_time": "2025-04-19T22:10:00.000Z", "end_date_time": "2025-04-19T22:20:00.000Z", "tags": [], "is_listed": true, "meta_data": {"tickets_issued": 2136, "tickets_available": 0, "tickets_issued_and_invalid": 2101, "tickets_issued_and_valid": 35, "last_ticket_created_at": "2025-04-17T20:47:15.757Z"}, "__v": 0, "created_at": "2024-12-16T20:16:10.654Z", "updated_at": "2025-04-17T20:47:16.327Z", "id": "67608a88e4a20e123832089f", "local_date_and_time": {"timezone": "GMT-10:00", "timezone_short": "GMT-10", "start_date": "4/19/2025", "start_time": "12:10 PM", "start_day_of_the_week": "Saturday", "end_date": "4/19/2025", "end_time": "12:20 PM", "end_day_of_the_week": "Saturday", "last_ticket_created_at": "Apr 17 at 10:47:15 AM"}}, {"event_id": "607fcb1a9196e149ac206742", "session_number": 35725, "app_id": "hanauma_bay", "location": {"id": "604bff314dde50e2de52c0e5", "name": "Hanauma Bay Orientation"}, "capacity": 35, "start_date_time": "2025-04-19T22:20:00.000Z", "end_date_time": "2025-04-19T22:30:00.000Z", "tags": [], "is_listed": true, "meta_data": {"tickets_issued": 706, "tickets_available": 0, "tickets_issued_and_invalid": 671, "tickets_issued_and_valid": 35, "last_ticket_created_at": "2025-04-17T20:30:23.392Z"}, "__v": 0, "created_at": "2024-12-16T20:16:10.655Z", "updated_at": "2025-04-17T20:30:23.559Z", "id": "67608a88e4a20e12383208a0", "local_date_and_time": {"timezone": "GMT-10:00", "timezone_short": "GMT-10", "start_date": "4/19/2025", "start_time": "12:20 PM", "start_day_of_the_week": "Saturday", "end_date": "4/19/2025", "end_time": "12:30 PM", "end_day_of_the_week": "Saturday", "last_ticket_created_at": "Apr 17 at 10:30:23 AM"}}, {"event_id": "607fcb1a9196e149ac206742", "session_number": 35726, "app_id": "hanauma_bay", "location": {"id": "604bff314dde50e2de52c0e5", "name": "Hanauma Bay Orientation"}, "capacity": 35, "start_date_time": "2025-04-19T22:30:00.000Z", "end_date_time": "2025-04-19T22:40:00.000Z", "tags": [], "is_listed": true, "meta_data": {"tickets_issued": 829, "tickets_available": 0, "tickets_issued_and_invalid": 794, "tickets_issued_and_valid": 35, "last_ticket_created_at": "2025-04-17T20:47:56.867Z"}, "__v": 0, "created_at": "2024-12-16T20:16:10.655Z", "updated_at": "2025-04-17T22:03:36.236Z", "id": "67608a88e4a20e12383208a1", "local_date_and_time": {"timezone": "GMT-10:00", "timezone_short": "GMT-10", "start_date": "4/19/2025", "start_time": "12:30 PM", "start_day_of_the_week": "Saturday", "end_date": "4/19/2025", "end_time": "12:40 PM", "end_day_of_the_week": "Saturday", "last_ticket_created_at": "Apr 17 at 10:47:56 AM"}}, {"event_id": "607fcb1a9196e149ac206742", "session_number": 35727, "app_id": "hanauma_bay", "location": {"id": "604bff314dde50e2de52c0e5", "name": "Hanauma Bay Orientation"}, "capacity": 35, "start_date_time": "2025-04-19T22:40:00.000Z", "end_date_time": "2025-04-19T23:00:00.000Z", "tags": [], "is_listed": true, "meta_data": {"tickets_issued": 1913, "tickets_available": 0, "tickets_issued_and_invalid": 1878, "tickets_issued_and_valid": 35, "last_ticket_created_at": "2025-04-17T20:53:51.150Z"}, "__v": 0, "created_at": "2024-12-16T20:16:10.655Z", "updated_at": "2025-04-17T20:53:51.550Z", "id": "67608a88e4a20e12383208a2", "local_date_and_time": {"timezone": "GMT-10:00", "timezone_short": "GMT-10", "start_date": "4/19/2025", "start_time": "12:40 PM", "start_day_of_the_week": "Saturday", "end_date": "4/19/2025", "end_time": "1:00 PM", "end_day_of_the_week": "Saturday", "last_ticket_created_at": "Apr 17 at 10:53:51 AM"}}, {"event_id": "607fcb1a9196e149ac206742", "session_number": 35728, "app_id": "hanauma_bay", "location": {"id": "604bff314dde50e2de52c0e5", "name": "Hanauma Bay Orientation"}, "capacity": 35, "start_date_time": "2025-04-19T23:00:00.000Z", "end_date_time": "2025-04-19T23:10:00.000Z", "tags": [], "is_listed": true, "meta_data": {"tickets_issued": 1857, "tickets_available": 0, "tickets_issued_and_invalid": 1822, "tickets_issued_and_valid": 35, "last_ticket_created_at": "2025-04-17T20:52:59.831Z"}, "__v": 0, "created_at": "2024-12-16T20:16:10.655Z", "updated_at": "2025-04-17T20:53:00.154Z", "id": "67608a88e4a20e12383208a3", "local_date_and_time": {"timezone": "GMT-10:00", "timezone_short": "GMT-10", "start_date": "4/19/2025", "start_time": "1:00 PM", "start_day_of_the_week": "Saturday", "end_date": "4/19/2025", "end_time": "1:10 PM", "end_day_of_the_week": "Saturday", "last_ticket_created_at": "Apr 17 at 10:52:59 AM"}}, {"event_id": "607fcb1a9196e149ac206742", "session_number": 35729, "app_id": "hanauma_bay", "location": {"id": "604bff314dde50e2de52c0e5", "name": "Hanauma Bay Orientation"}, "capacity": 35, "start_date_time": "2025-04-19T23:10:00.000Z", "end_date_time": "2025-04-19T23:20:00.000Z", "tags": [], "is_listed": true, "meta_data": {"tickets_issued": 954, "tickets_available": 0, "tickets_issued_and_invalid": 919, "tickets_issued_and_valid": 35, "last_ticket_created_at": "2025-04-17T21:03:36.154Z"}, "__v": 0, "created_at": "2024-12-16T20:16:10.655Z", "updated_at": "2025-04-17T21:03:36.532Z", "id": "67608a88e4a20e12383208a4", "local_date_and_time": {"timezone": "GMT-10:00", "timezone_short": "GMT-10", "start_date": "4/19/2025", "start_time": "1:10 PM", "start_day_of_the_week": "Saturday", "end_date": "4/19/2025", "end_time": "1:20 PM", "end_day_of_the_week": "Saturday", "last_ticket_created_at": "Apr 17 at 11:03:36 AM"}}, {"event_id": "607fcb1a9196e149ac206742", "session_number": 35730, "app_id": "hanauma_bay", "location": {"id": "604bff314dde50e2de52c0e5", "name": "Hanauma Bay Orientation"}, "capacity": 30, "start_date_time": "2025-04-19T23:20:00.000Z", "end_date_time": "2025-04-19T23:30:00.000Z", "tags": [], "is_listed": true, "meta_data": {"tickets_issued": 3450, "tickets_available": 0, "tickets_issued_and_invalid": 3420, "tickets_issued_and_valid": 30, "last_ticket_created_at": "2025-04-17T20:44:45.330Z"}, "__v": 0, "created_at": "2024-12-16T20:16:10.655Z", "updated_at": "2025-04-17T20:44:46.059Z", "id": "67608a88e4a20e12383208a5", "local_date_and_time": {"timezone": "GMT-10:00", "timezone_short": "GMT-10", "start_date": "4/19/2025", "start_time": "1:20 PM", "start_day_of_the_week": "Saturday", "end_date": "4/19/2025", "end_time": "1:30 PM", "end_day_of_the_week": "Saturday", "last_ticket_created_at": "Apr 17 at 10:44:45 AM"}}]}}